Workbook

Sheet README
A1: SG Bloomberg Historical Pull — Quant Trading
A3: Purpose
A4: Pull SGX history from Bloomberg into the 4 CSV layouts this project needs under data/sg/raw/, then run: python main.py --market sg --skip-download
A6: Sheets
A7: 1. Control — start/end dates and pull settings (edit these first)
A8: 2. Universe — Yahoo .SI tickers ↔ Bloomberg SP Equity codes
A9: 3. Prices — each ticker Date|Value BDH block (→ price_data.csv)
A10: 4. Book — each ticker Date|Value BDH Per=M (→ book_data.csv)
A11: 5. Categories — sector + market cap BDP (→ categorizations_data.csv)
A12: 6. Dividends — BDS DVD_HIST_ALL for EVERY ticker (side-by-side blocks)
A13: 7. Dividends_Detail — one-ticker DVD_HIST + Regular vs Special sums
A14: 8. FAQ — BQ error / Special dividends / why DBS
... A32: TA-Lib / OHLCV not required — this project uses adjusted close only.

Sheet Control
A1: Parameter | B1: Value
A2: StartDate | B2: =EDATE(TODAY(),-60) | C2: Rolling 5 years (60 months). Hardcode e.g. 2021-09-01 to match config if preferred.
A3: EndDate | B3: =TODAY()-1 | C3: Leave as TODAY()-1 or hardcode e.g. 2026-09-04
A4: PriceField | B4: PX_LAST | C4: Adjusted via BDH overrides on Prices sheet
A5: BookField | B5: BOOK_VAL_PER_SH | C5: Book value per share (BDH)
A6: BookPeriod | B6: M | C6: Monthly BDH periodicity for book value (was Q)
A7: PricePeriod | B7: D | C7: Daily
A8: DivField | B8: DVD_HIST_ALL | C8: Bloomberg dividend history via BDS (not BDH)
A9: Currency | B9: SGD | C9: Informational
A10: Exchange | B10: SP / SGX | C10: Bloomberg yellow-key Equity, SGX
A11: OutputFolder | B11: C:\Users\taiji\Desktop\Python Project\Quant Learning Journey\quant-trading\data\sg\raw | C11: Where CSVs should land
A12: BDH price overrides (already embedded in Prices formulas)
A13: CshAdjNormal=Y | CshAdjAbnormal=Y | CapChg=Y | Dir=V | Dts=S | Sort=A | Fill=P | Days=A

Sheet Universe
A1: YahooTicker | B1: BloombergTicker | C1: Include | D1: Name_BDP | E1: Last_BDP | F1: Sector_BDP | G1: MktCap_BDP
A2: D05.SI | B2: D05 SP Equity | C2: YES | D2: =BDP(B2,"NAME") | E2: =BDP(B2,"PX_LAST") | F2: =BDP(B2,"GICS_SECTOR_NAME") | G2: =BDP(B2,"CUR_MKT_CAP")
A3: O39.SI | B3: O39 SP Equity | C3: YES | D3: =BDP(B3,"NAME") | E3: =BDP(B3,"PX_LAST") | F3: =BDP(B3,"GICS_SECTOR_NAME") | G3: =BDP(B3,"CUR_MKT_CAP")
A4: Z74.SI | B4: Z74 SP Equity | C4: YES | D4: =BDP(B4,"NAME") | E4: =BDP(B4,"PX_LAST") | F4: =BDP(B4,"GICS_SECTOR_NAME") | G4: =BDP(B4,"CUR_MKT_CAP")
A5: U11.SI | B5: U11 SP Equity | C5: YES | D5: =BDP(B5,"NAME") | E5: =BDP(B5,"PX_LAST") | F5: =BDP(B5,"GICS_SECTOR_NAME") | G5: =BDP(B5,"CUR_MKT_CAP")
A6: S63.SI | B6: S63 SP Equity | C6: YES | D6: =BDP(B6,"NAME") | E6: =BDP(B6,"PX_LAST") | F6: =BDP(B6,"GICS_SECTOR_NAME") | G6: =BDP(B6,"CUR_MKT_CAP")
A7: S68.SI | B7: S68 SP Equity | C7: YES | D7: =BDP(B7,"NAME") | E7: =BDP(B7,"PX_LAST") | F7: =BDP(B7,"GICS_SECTOR_NAME") | G7: =BDP(B7,"CUR_MKT_CAP")
A8: J36.SI | B8: J36 SP Equity | C8: YES | D8: =BDP(B8,"NAME") | E8: =BDP(B8,"PX_LAST") | F8: =BDP(B8,"GICS_SECTOR_NAME") | G8: =BDP(B8,"CUR_MKT_CAP")
A9: C6L.SI | B9: C6L SP Equity | C9: YES | D9: =BDP(B9,"NAME") | E9: =BDP(B9,"PX_LAST") | F9: =BDP(B9,"GICS_SECTOR_NAME") | G9: =BDP(B9,"CUR_MKT_CAP")
A10: F34.SI | B10: F34 SP Equity | C10: YES | D10: =BDP(B10,"NAME") | E10: =BDP(B10,"PX_LAST") | F10: =BDP(B10,"GICS_SECTOR_NAME") | G10: =BDP(B10,"CUR_MKT_CAP")
A11: H78.SI | B11: H78 SP Equity | C11: YES | D11: =BDP(B11,"NAME") | E11: =BDP(B11,"PX_LAST") | F11: =BDP(B11,"GICS_SECTOR_NAME") | G11: =BDP(B11,"CUR_MKT_CAP")
A12: BN4.SI | B12: BN4 SP Equity | C12: YES | D12: =BDP(B12,"NAME") | E12: =BDP(B12,"PX_LAST") | F12: =BDP(B12,"GICS_SECTOR_NAME") | G12: =BDP(B12,"CUR_MKT_CAP")
A13: C38U.SI | B13: C38U SP Equity | C13: YES | D13: =BDP(B13,"NAME") | E13: =BDP(B13,"PX_LAST") | F13: =BDP(B13,"GICS_SECTOR_NAME") | G13: =BDP(B13,"CUR_MKT_CAP")
... A81: ES3.SI | B81: ES3 SP Equity | C81: BENCH | D81: =BDP(B81,"NAME") | E81: =BDP(B81,"PX_LAST") | F81: =BDP(B81,"GICS_SECTOR_NAME") | G81: =BDP(B81,"CUR_MKT_CAP")

Sheet Prices
A1: Each ticker = 2 columns (Date | Value) with Dts=S. NOT DBS-only dates. Scroll right. Run bbg_to_csv.py to merge into wide price_data.csv.
A3: D05.SI | B3: Value | C3: O39.SI | D3: Value | E3: Z74.SI | F3: Value | G3: U11.SI | H3: Value | I3: S63.SI | J3: Value | K3: S68.SI | L3: Value | M3: J36.SI | N3: Value | O3: C6L.SI | P3: Value | Q3: F34.SI | R3: Value | S3: H78.SI | T3: Value | U3: BN4.SI | V3: Value | W3: C38U.SI | X3: Value | Y3: U14.SI | Z3: Value | AA3: 5E2.SI | AB3: Value | AC3: G13.SI | AD3: Value | AE3: S58.SI | AF3: Value | AG3: N2IU.SI | AH3: Value | AI3: C09.SI | AJ3: Value | AK3: D01.SI | AL3: Value | AM3: M44U.SI | AN3: Value | AO3: EB5.SI | AP3: Value | AQ3: ME8U.SI | AR3: Value | AS3: AJBU.SI | AT3: Value | AU3: VC2.SI | AV3: Value | AW3: U06.SI | AX3: Value | AY3: OV8.SI | AZ3: Value | BA3: V03.SI | BB3: Value | BC3: J69U.SI | BD3: Value | BE3: T82U.SI | BF3: Value | BG3: K71U.SI | BH3: Value | BI3: U10.SI | BJ3: Value | BK3: TQ5.SI | BL3: Value | BM3: CJL.SI | BN3: Value | BO3: BUOU.SI | BP3: Value | BQ3: S59.SI | BR3: Value | BS3: E5H.SI | BT3: Value | BU3: H02.SI | BV3: Value | BW3: HMN.SI | BX3: Value | BY3: A7RU.SI | BZ3: Value | CA3: P8Z.SI | CB3: Value | CC3: C52.SI | CD3: Value | CE3: AWX.SI | CF3: Value | CG3: AIY.SI | CH3: Value | CI3: C2PU.SI | CJ3: Value | CK3: F17.SI | CL3: Value | CM3: H15.SI | CN3: Value | CO3: H22.SI | CP3: Value | CQ3: 558.SI | CR3: Value | CS3: NS8U.SI | CT3: Value | CU3: 8Y.SI | CV3: Value | CW3: F99.SI | CX3: Value | CY3: TS0U.SI | CZ3: Value | DA3: 9A4U.SI | DB3: Value | DC3: 8C8U.SI | DD3: Value | DE3: SEB.SI | DF3: Value | DG3: Z25.SI | DH3: Value | DI3: AP4.SI | DJ3: Value | DK3: P40U.SI | DL3: Value | DM3: B61.SI | DN3: Value | DO3: NTDU.SI | DP3: Value | DQ3: W05.SI | DR3: Value | DS3: Q5T.SI | DT3: Value | DU3: BEC.SI | DV3: Value | DW3: E28.SI | DX3: Value | DY3: UIBU.SI | DZ3: Value | EA3: AU8U.SI | EB3: Value | EC3: P52.SI | ED3: Value | EE3: S41.SI | EF3: Value | EG3: S61.SI | EH3: Value | EI3: PCT.SI | EJ3: Value | EK3: ADN.SI | EL3: Value | EM3: F9D.SI | EN3: Value | EO3: FHH.SI | EP3: Value | EQ3: J85.SI | ER3: Value | ES3: T6I.SI | ET3: Value | EU3: RE4.SI | EV3: Value | EW3: 544.SI | EX3: Value | EY3: CRPU.SI | EZ3: Value | FA3: DCRU.SI | FB3: Value
A4: =BDH(Universe!B2,"PX_LAST",Control!$B$2,Control!$B$3,"Dir=V","Dts=S","Sort=A","CshAdjNormal=Y","CshAdjAbnormal=Y","CapChg=Y","Fill=P","Days=A") | C4: =BDH(Universe!B3,"PX_LAST",Control!$B$2,Control!$B$3,"Dir=V","Dts=S","Sort=A","CshAdjNormal=Y","CshAdjAbnormal=Y","CapChg=Y","Fill=P","Days=A") | E4: =BDH(Universe!B4,"PX_LAST",Control!$B$2,Control!$B$3,"Dir=V","Dts=S","Sort=A","CshAdjNormal=Y","CshAdjAbnormal=Y","CapChg=Y","Fill=P","Days=A") | G4: =BDH(Universe!B5,"PX_LAST",Control!$B$2,Control!$B$3,"Dir=V","Dts=S","Sort=A","CshAdjNormal=Y","CshAdjAbnormal=Y","CapChg=Y","Fill=P","Days=A") | I4: =BDH(Universe!B6,"PX_LAST",Control!$B$2,Control!$B$3,"Dir=V","Dts=S","Sort=A","CshAdjNormal=Y","CshAdjAbnormal=Y","CapChg=Y","Fill=P","Days=A") | K4: =BDH(Universe!B7,"PX_LAST",Control!$B$2,Control!$B$3,"Dir=V","Dts=S","Sort=A","CshAdjNormal=Y","CshAdjAbnormal=Y","CapChg=Y","Fill=P","Days=A") | M4: =BDH(Universe!B8,"PX_LAST",Control!$B$2,Control!$B$3,"Dir=V","Dts=S","Sort=A","CshAdjNormal=Y","CshAdjAbnormal=Y","CapChg=Y","Fill=P","Days=A") | O4: =BDH(Universe!B9,"PX_LAST",Control!$B$2,Control!$B$3,"Dir=V","Dts=S","Sort=A","CshAdjNormal=Y","CshAdjAbnormal=Y","CapChg=Y","Fill=P","Days=A") | Q4: =BDH(Universe!B10,"PX_LAST",Control!$B$2,Control!$B$3,"Dir=V","Dts=S","Sort=A","CshAdjNormal=Y","CshAdjAbnormal=Y","CapChg=Y","Fill=P","Days=A") | S4: =BDH(Universe!B11,"PX_LAST",Control!$B$2,Control!$B$3,"Dir=V","Dts=S","Sort=A","CshAdjNormal=Y","CshAdjAbnormal=Y","CapChg=Y","Fill=P","Days=A") | U4: =BDH(Universe!B12,"PX_LAST",Control!$B$2,Control!$B$3,"Dir=V","Dts=S","Sort=A","CshAdjNormal=Y","CshAdjAbnormal=Y","CapChg=Y","Fill=P","Days=A") | W4: =BDH(Universe!B13,"PX_LAST",Control!$B$2,Control!$B$3,"Dir=V","Dts=S","Sort=A","CshAdjNormal=Y","CshAdjAbnormal=Y","CapChg=Y","Fill=P","Days=A") | Y4: =BDH(Universe!B14,"PX_LAST",Control!$B$2,Control!$B$3,"Dir=V","Dts=S","Sort=A","CshAdjNormal=Y","CshAdjAbnormal=Y","CapChg=Y","Fill=P","Days=A") | AA4: =BDH(Universe!B15,"PX_LAST",Control!$B$2,Control!$B$3,"Dir=V","Dts=S","Sort=A","CshAdjNormal=Y","CshAdjAbnormal=Y","CapChg=Y","Fill=P","Days=A") | AC4: =BDH(Universe!B16,"PX_LAST",Control!$B$2,Control!$B$3,"Dir=V","Dts=S","Sort=A","CshAdjNormal=Y","CshAdjAbnormal=Y","CapChg=Y","Fill=P","Days=A") | AE4: =BDH(Universe!B17,"PX_LAST",Control!$B$2,Control!$B$3,"Dir=V","Dts=S","Sort=A","CshAdjNormal=Y","CshAdjAbnormal=Y","CapChg=Y","Fill=P","Days=A") | AG4: =BDH(Universe!B18,"PX_LAST",Control!$B$2,Control!$B$3,"Dir=V","Dts=S","Sort=A","CshAdjNormal=Y","CshAdjAbnormal=Y","CapChg=Y","Fill=P","Days=A") | AI4: =BDH(Universe!B19,"PX_LAST",Control!$B$2,Control!$B$3,"Dir=V","Dts=S","Sort=A","CshAdjNormal=Y","CshAdjAbnormal=Y","CapChg=Y","Fill=P","Days=A") | AK4: =BDH(Universe!B20,"PX_LAST",Control!$B$2,Control!$B$3,"Dir=V","Dts=S","Sort=A","CshAdjNormal=Y","CshAdjAbnormal=Y","CapChg=Y","Fill=P","Days=A") | AM4: =BDH(Universe!B21,"PX_LAST",Control!$B$2,Control!$B$3,"Dir=V","Dts=S","Sort=A","CshAdjNormal=Y","CshAdjAbnormal=Y","CapChg=Y","Fill=P","Days=A") | AO4: =BDH(Universe!B22,"PX_LAST",Control!$B$2,Control!$B$3,"Dir=V","Dts=S","Sort=A","CshAdjNormal=Y","CshAdjAbnormal=Y","CapChg=Y","Fill=P","Days=A") | AQ4: =BDH(Universe!B23,"PX_LAST",Control!$B$2,Control!$B$3,"Dir=V","Dts=S","Sort=A","CshAdjNormal=Y","CshAdjAbnormal=Y","CapChg=Y","Fill=P","Days=A") | AS4: =BDH(Universe!B24,"PX_LAST",Control!$B$2,Control!$B$3,"Dir=V","Dts=S","Sort=A","CshAdjNormal=Y","CshAdjAbnormal=Y","CapChg=Y","Fill=P","Days=A") | AU4: =BDH(Universe!B25,"PX_LAST",Control!$B$2,Control!$B$3,"Dir=V","Dts=S","Sort=A","CshAdjNormal=Y","CshAdjAbnormal=Y","CapChg=Y","Fill=P","Days=A") | AW4: =BDH(Universe!B26,"PX_LAST",Control!$B$2,Control!$B$3,"Dir=V","Dts=S","Sort=A","CshAdjNormal=Y","CshAdjAbnormal=Y","CapChg=Y","Fill=P","Days=A") | AY4: =BDH(Universe!B27,"PX_LAST",Control!$B$2,Control!$B$3,"Dir=V","Dts=S","Sort=A","CshAdjNormal=Y","CshAdjAbnormal=Y","CapChg=Y","Fill=P","Days=A") | BA4: =BDH(Universe!B28,"PX_LAST",Control!$B$2,Control!$B$3,"Dir=V","Dts=S","Sort=A","CshAdjNormal=Y","CshAdjAbnormal=Y","CapChg=Y","Fill=P","Days=A") | BC4: =BDH(Universe!B29,"PX_LAST",Control!$B$2,Control!$B$3,"Dir=V","Dts=S","Sort=A","CshAdjNormal=Y","CshAdjAbnormal=Y","CapChg=Y","Fill=P","Days=A") | BE4: =BDH(Universe!B30,"PX_LAST",Control!$B$2,Control!$B$3,"Dir=V","Dts=S","Sort=A","CshAdjNormal=Y","CshAdjAbnormal=Y","CapChg=Y","Fill=P","Days=A") | BG4: =BDH(Universe!B31,"PX_LAST",Control!$B$2,Control!$B$3,"Dir=V","Dts=S","Sort=A","CshAdjNormal=Y","CshAdjAbnormal=Y","CapChg=Y","Fill=P","Days=A") | BI4: =BDH(Universe!B32,"PX_LAST",Control!$B$2,Control!$B$3,"Dir=V","Dts=S","Sort=A","CshAdjNormal=Y","CshAdjAbnormal=Y","CapChg=Y","Fill=P","Days=A") | BK4: =BDH(Universe!B33,"PX_LAST",Control!$B$2,Control!$B$3,"Dir=V","Dts=S","Sort=A","CshAdjNormal=Y","CshAdjAbnormal=Y","CapChg=Y","Fill=P","Days=A") | BM4: =BDH(Universe!B34,"PX_LAST",Control!$B$2,Control!$B$3,"Dir=V","Dts=S","Sort=A","CshAdjNormal=Y","CshAdjAbnormal=Y","CapChg=Y","Fill=P","Days=A") | BO4: =BDH(Universe!B35,"PX_LAST",Control!$B$2,Control!$B$3,"Dir=V","Dts=S","Sort=A","CshAdjNormal=Y","CshAdjAbnormal=Y","CapChg=Y","Fill=P","Days=A") | BQ4: =BDH(Universe!B36,"PX_LAST",Control!$B$2,Control!$B$3,"Dir=V","Dts=S","Sort=A","CshAdjNormal=Y","CshAdjAbnormal=Y","CapChg=Y","Fill=P","Days=A") | BS4: =BDH(Universe!B37,"PX_LAST",Control!$B$2,Control!$B$3,"Dir=V","Dts=S","Sort=A","CshAdjNormal=Y","CshAdjAbnormal=Y","CapChg=Y","Fill=P","Days=A") | BU4: =BDH(Universe!B38,"PX_LAST",Control!$B$2,Control!$B$3,"Dir=V","Dts=S","Sort=A","CshAdjNormal=Y","CshAdjAbnormal=Y","CapChg=Y","Fill=P","Days=A") | BW4: =BDH(Universe!B39,"PX_LAST",Control!$B$2,Control!$B$3,"Dir=V","Dts=S","Sort=A","CshAdjNormal=Y","CshAdjAbnormal=Y","CapChg=Y","Fill=P","Days=A") | BY4: =BDH(Universe!B40,"PX_LAST",Control!$B$2,Control!$B$3,"Dir=V","Dts=S","Sort=A","CshAdjNormal=Y","CshAdjAbnormal=Y","CapChg=Y","Fill=P","Days=A") | CA4: =BDH(Universe!B41,"PX_LAST",Control!$B$2,Control!$B$3,"Dir=V","Dts=S","Sort=A","CshAdjNormal=Y","CshAdjAbnormal=Y","CapChg=Y","Fill=P","Days=A") | CC4: =BDH(Universe!B42,"PX_LAST",Control!$B$2,Control!$B$3,"Dir=V","Dts=S","Sort=A","CshAdjNormal=Y","CshAdjAbnormal=Y","CapChg=Y","Fill=P","Days=A") | CE4: =BDH(Universe!B43,"PX_LAST",Control!$B$2,Control!$B$3,"Dir=V","Dts=S","Sort=A","CshAdjNormal=Y","CshAdjAbnormal=Y","CapChg=Y","Fill=P","Days=A") | CG4: =BDH(Universe!B44,"PX_LAST",Control!$B$2,Control!$B$3,"Dir=V","Dts=S","Sort=A","CshAdjNormal=Y","CshAdjAbnormal=Y","CapChg=Y","Fill=P","Days=A") | CI4: =BDH(Universe!B45,"PX_LAST",Control!$B$2,Control!$B$3,"Dir=V","Dts=S","Sort=A","CshAdjNormal=Y","CshAdjAbnormal=Y","CapChg=Y","Fill=P","Days=A") | CK4: =BDH(Universe!B46,"PX_LAST",Control!$B$2,Control!$B$3,"Dir=V","Dts=S","Sort=A","CshAdjNormal=Y","CshAdjAbnormal=Y","CapChg=Y","Fill=P","Days=A") | CM4: =BDH(Universe!B47,"PX_LAST",Control!$B$2,Control!$B$3,"Dir=V","Dts=S","Sort=A","CshAdjNormal=Y","CshAdjAbnormal=Y","CapChg=Y","Fill=P","Days=A") | CO4: =BDH(Universe!B48,"PX_LAST",Control!$B$2,Control!$B$3,"Dir=V","Dts=S","Sort=A","CshAdjNormal=Y","CshAdjAbnormal=Y","CapChg=Y","Fill=P","Days=A") | CQ4: =BDH(Universe!B49,"PX_LAST",Control!$B$2,Control!$B$3,"Dir=V","Dts=S","Sort=A","CshAdjNormal=Y","CshAdjAbnormal=Y","CapChg=Y","Fill=P","Days=A") | CS4: =BDH(Universe!B50,"PX_LAST",Control!$B$2,Control!$B$3,"Dir=V","Dts=S","Sort=A","CshAdjNormal=Y","CshAdjAbnormal=Y","CapChg=Y","Fill=P","Days=A") | CU4: =BDH(Universe!B51,"PX_LAST",Control!$B$2,Control!$B$3,"Dir=V","Dts=S","Sort=A","CshAdjNormal=Y","CshAdjAbnormal=Y","CapChg=Y","Fill=P","Days=A") | CW4: =BDH(Universe!B52,"PX_LAST",Control!$B$2,Control!$B$3,"Dir=V","Dts=S","Sort=A","CshAdjNormal=Y","CshAdjAbnormal=Y","CapChg=Y","Fill=P","Days=A") | CY4: =BDH(Universe!B53,"PX_LAST",Control!$B$2,Control!$B$3,"Dir=V","Dts=S","Sort=A","CshAdjNormal=Y","CshAdjAbnormal=Y","CapChg=Y","Fill=P","Days=A") | DA4: =BDH(Universe!B54,"PX_LAST",Control!$B$2,Control!$B$3,"Dir=V","Dts=S","Sort=A","CshAdjNormal=Y","CshAdjAbnormal=Y","CapChg=Y","Fill=P","Days=A") | DC4: =BDH(Universe!B55,"PX_LAST",Control!$B$2,Control!$B$3,"Dir=V","Dts=S","Sort=A","CshAdjNormal=Y","CshAdjAbnormal=Y","CapChg=Y","Fill=P","Days=A") | DE4: =BDH(Universe!B56,"PX_LAST",Control!$B$2,Control!$B$3,"Dir=V","Dts=S","Sort=A","CshAdjNormal=Y","CshAdjAbnormal=Y","CapChg=Y","Fill=P","Days=A") | DG4: =BDH(Universe!B57,"PX_LAST",Control!$B$2,Control!$B$3,"Dir=V","Dts=S","Sort=A","CshAdjNormal=Y","CshAdjAbnormal=Y","CapChg=Y","Fill=P","Days=A") | DI4: =BDH(Universe!B58,"PX_LAST",Control!$B$2,Control!$B$3,"Dir=V","Dts=S","Sort=A","CshAdjNormal=Y","CshAdjAbnormal=Y","CapChg=Y","Fill=P","Days=A") | DK4: =BDH(Universe!B59,"PX_LAST",Control!$B$2,Control!$B$3,"Dir=V","Dts=S","Sort=A","CshAdjNormal=Y","CshAdjAbnormal=Y","CapChg=Y","Fill=P","Days=A") | DM4: =BDH(Universe!B60,"PX_LAST",Control!$B$2,Control!$B$3,"Dir=V","Dts=S","Sort=A","CshAdjNormal=Y","CshAdjAbnormal=Y","CapChg=Y","Fill=P","Days=A") | DO4: =BDH(Universe!B61,"PX_LAST",Control!$B$2,Control!$B$3,"Dir=V","Dts=S","Sort=A","CshAdjNormal=Y","CshAdjAbnormal=Y","CapChg=Y","Fill=P","Days=A") | DQ4: =BDH(Universe!B62,"PX_LAST",Control!$B$2,Control!$B$3,"Dir=V","Dts=S","Sort=A","CshAdjNormal=Y","CshAdjAbnormal=Y","CapChg=Y","Fill=P","Days=A") | DS4: =BDH(Universe!B63,"PX_LAST",Control!$B$2,Control!$B$3,"Dir=V","Dts=S","Sort=A","CshAdjNormal=Y","CshAdjAbnormal=Y","CapChg=Y","Fill=P","Days=A") | DU4: =BDH(Universe!B64,"PX_LAST",Control!$B$2,Control!$B$3,"Dir=V","Dts=S","Sort=A","CshAdjNormal=Y","CshAdjAbnormal=Y","CapChg=Y","Fill=P","Days=A") | DW4: =BDH(Universe!B65,"PX_LAST",Control!$B$2,Control!$B$3,"Dir=V","Dts=S","Sort=A","CshAdjNormal=Y","CshAdjAbnormal=Y","CapChg=Y","Fill=P","Days=A") | DY4: =BDH(Universe!B66,"PX_LAST",Control!$B$2,Control!$B$3,"Dir=V","Dts=S","Sort=A","CshAdjNormal=Y","CshAdjAbnormal=Y","CapChg=Y","Fill=P","Days=A") | EA4: =BDH(Universe!B67,"PX_LAST",Control!$B$2,Control!$B$3,"Dir=V","Dts=S","Sort=A","CshAdjNormal=Y","CshAdjAbnormal=Y","CapChg=Y","Fill=P","Days=A") | EC4: =BDH(Universe!B68,"PX_LAST",Control!$B$2,Control!$B$3,"Dir=V","Dts=S","Sort=A","CshAdjNormal=Y","CshAdjAbnormal=Y","CapChg=Y","Fill=P","Days=A") | EE4: =BDH(Universe!B69,"PX_LAST",Control!$B$2,Control!$B$3,"Dir=V","Dts=S","Sort=A","CshAdjNormal=Y","CshAdjAbnormal=Y","CapChg=Y","Fill=P","Days=A") | EG4: =BDH(Universe!B70,"PX_LAST",Control!$B$2,Control!$B$3,"Dir=V","Dts=S","Sort=A","CshAdjNormal=Y","CshAdjAbnormal=Y","CapChg=Y","Fill=P","Days=A") | EI4: =BDH(Universe!B71,"PX_LAST",Control!$B$2,Control!$B$3,"Dir=V","Dts=S","Sort=A","CshAdjNormal=Y","CshAdjAbnormal=Y","CapChg=Y","Fill=P","Days=A") | EK4: =BDH(Universe!B72,"PX_LAST",Control!$B$2,Control!$B$3,"Dir=V","Dts=S","Sort=A","CshAdjNormal=Y","CshAdjAbnormal=Y","CapChg=Y","Fill=P","Days=A") | EM4: =BDH(Universe!B73,"PX_LAST",Control!$B$2,Control!$B$3,"Dir=V","Dts=S","Sort=A","CshAdjNormal=Y","CshAdjAbnormal=Y","CapChg=Y","Fill=P","Days=A") | EO4: =BDH(Universe!B74,"PX_LAST",Control!$B$2,Control!$B$3,"Dir=V","Dts=S","Sort=A","CshAdjNormal=Y","CshAdjAbnormal=Y","CapChg=Y","Fill=P","Days=A") | EQ4: =BDH(Universe!B75,"PX_LAST",Control!$B$2,Control!$B$3,"Dir=V","Dts=S","Sort=A","CshAdjNormal=Y","CshAdjAbnormal=Y","CapChg=Y","Fill=P","Days=A") | ES4: =BDH(Universe!B76,"PX_LAST",Control!$B$2,Control!$B$3,"Dir=V","Dts=S","Sort=A","CshAdjNormal=Y","CshAdjAbnormal=Y","CapChg=Y","Fill=P","Days=A") | EU4: =BDH(Universe!B77,"PX_LAST",Control!$B$2,Control!$B$3,"Dir=V","Dts=S","Sort=A","CshAdjNormal=Y","CshAdjAbnormal=Y","CapChg=Y","Fill=P","Days=A") | EW4: =BDH(Universe!B78,"PX_LAST",Control!$B$2,Control!$B$3,"Dir=V","Dts=S","Sort=A","CshAdjNormal=Y","CshAdjAbnormal=Y","CapChg=Y","Fill=P","Days=A") | EY4: =BDH(Universe!B79,"PX_LAST",Control!$B$2,Control!$B$3,"Dir=V","Dts=S","Sort=A","CshAdjNormal=Y","CshAdjAbnormal=Y","CapChg=Y","Fill=P","Days=A") | FA4: =BDH(Universe!B80,"PX_LAST",Control!$B$2,Control!$B$3,"Dir=V","Dts=S","Sort=A","CshAdjNormal=Y","CshAdjAbnormal=Y","CapChg=Y","Fill=P","Days=A")

Sheet Prices_Index
A1: YahooTicker | B1: BloombergTicker | C1: StartCol | D1: ExcelCol | E1: BDH_Cell
A2: D05.SI | B2: D05 SP Equity | C2: 1 | D2: A | E2: A4
A3: O39.SI | B3: O39 SP Equity | C3: 3 | D3: C | E3: C4
A4: Z74.SI | B4: Z74 SP Equity | C4: 5 | D4: E | E4: E4
A5: U11.SI | B5: U11 SP Equity | C5: 7 | D5: G | E5: G4
A6: S63.SI | B6: S63 SP Equity | C6: 9 | D6: I | E6: I4
A7: S68.SI | B7: S68 SP Equity | C7: 11 | D7: K | E7: K4
A8: J36.SI | B8: J36 SP Equity | C8: 13 | D8: M | E8: M4
A9: C6L.SI | B9: C6L SP Equity | C9: 15 | D9: O | E9: O4
A10: F34.SI | B10: F34 SP Equity | C10: 17 | D10: Q | E10: Q4
A11: H78.SI | B11: H78 SP Equity | C11: 19 | D11: S | E11: S4
A12: BN4.SI | B12: BN4 SP Equity | C12: 21 | D12: U | E12: U4
A13: C38U.SI | B13: C38U SP Equity | C13: 23 | D13: W | E13: W4
... A80: DCRU.SI | B80: DCRU SP Equity | C80: 157 | D80: FA | E80: FA4

Sheet Prices_Notes
A1: Prices sheet notes
A2: Each ticker has its OWN dates (Dts=S) — not only DBS.
A3: Block layout: Row3 = Yahoo ticker | Value; Row4 = BDH spills Date + PX_LAST.
A4: See Prices_Index for column map (D05 starts col A, O39 starts col C, …).
A5: bbg_to_csv.py outer-joins all blocks on Date → wide price_data.csv.
A6: Fill=P / Days=A: edit formula if you want exchange trading days only.

Sheet Book
A1: Each ticker = 2 columns (Date | BOOK_VAL_PER_SH), Per=M, Dts=S. Every name has its own dates (not DBS-only).
A3: D05.SI | B3: Value | C3: O39.SI | D3: Value | E3: Z74.SI | F3: Value | G3: U11.SI | H3: Value | I3: S63.SI | J3: Value | K3: S68.SI | L3: Value | M3: J36.SI | N3: Value | O3: C6L.SI | P3: Value | Q3: F34.SI | R3: Value | S3: H78.SI | T3: Value | U3: BN4.SI | V3: Value | W3: C38U.SI | X3: Value | Y3: U14.SI | Z3: Value | AA3: 5E2.SI | AB3: Value | AC3: G13.SI | AD3: Value | AE3: S58.SI | AF3: Value | AG3: N2IU.SI | AH3: Value | AI3: C09.SI | AJ3: Value | AK3: D01.SI | AL3: Value | AM3: M44U.SI | AN3: Value | AO3: EB5.SI | AP3: Value | AQ3: ME8U.SI | AR3: Value | AS3: AJBU.SI | AT3: Value | AU3: VC2.SI | AV3: Value | AW3: U06.SI | AX3: Value | AY3: OV8.SI | AZ3: Value | BA3: V03.SI | BB3: Value | BC3: J69U.SI | BD3: Value | BE3: T82U.SI | BF3: Value | BG3: K71U.SI | BH3: Value | BI3: U10.SI | BJ3: Value | BK3: TQ5.SI | BL3: Value | BM3: CJL.SI | BN3: Value | BO3: BUOU.SI | BP3: Value | BQ3: S59.SI | BR3: Value | BS3: E5H.SI | BT3: Value | BU3: H02.SI | BV3: Value | BW3: HMN.SI | BX3: Value | BY3: A7RU.SI | BZ3: Value | CA3: P8Z.SI | CB3: Value | CC3: C52.SI | CD3: Value | CE3: AWX.SI | CF3: Value | CG3: AIY.SI | CH3: Value | CI3: C2PU.SI | CJ3: Value | CK3: F17.SI | CL3: Value | CM3: H15.SI | CN3: Value | CO3: H22.SI | CP3: Value | CQ3: 558.SI | CR3: Value | CS3: NS8U.SI | CT3: Value | CU3: 8Y.SI | CV3: Value | CW3: F99.SI | CX3: Value | CY3: TS0U.SI | CZ3: Value | DA3: 9A4U.SI | DB3: Value | DC3: 8C8U.SI | DD3: Value | DE3: SEB.SI | DF3: Value | DG3: Z25.SI | DH3: Value | DI3: AP4.SI | DJ3: Value | DK3: P40U.SI | DL3: Value | DM3: B61.SI | DN3: Value | DO3: NTDU.SI | DP3: Value | DQ3: W05.SI | DR3: Value | DS3: Q5T.SI | DT3: Value | DU3: BEC.SI | DV3: Value | DW3: E28.SI | DX3: Value | DY3: UIBU.SI | DZ3: Value | EA3: AU8U.SI | EB3: Value | EC3: P52.SI | ED3: Value | EE3: S41.SI | EF3: Value | EG3: S61.SI | EH3: Value | EI3: PCT.SI | EJ3: Value | EK3: ADN.SI | EL3: Value | EM3: F9D.SI | EN3: Value | EO3: FHH.SI | EP3: Value | EQ3: J85.SI | ER3: Value | ES3: T6I.SI | ET3: Value | EU3: RE4.SI | EV3: Value | EW3: 544.SI | EX3: Value | EY3: CRPU.SI | EZ3: Value | FA3: DCRU.SI | FB3: Value
A4: =BDH(Universe!B2,Control!$B$5,Control!$B$2,Control!$B$3,"Dir=V","Dts=S","Sort=A","Per=M","Fill=P") | C4: =BDH(Universe!B3,Control!$B$5,Control!$B$2,Control!$B$3,"Dir=V","Dts=S","Sort=A","Per=M","Fill=P") | E4: =BDH(Universe!B4,Control!$B$5,Control!$B$2,Control!$B$3,"Dir=V","Dts=S","Sort=A","Per=M","Fill=P") | G4: =BDH(Universe!B5,Control!$B$5,Control!$B$2,Control!$B$3,"Dir=V","Dts=S","Sort=A","Per=M","Fill=P") | I4: =BDH(Universe!B6,Control!$B$5,Control!$B$2,Control!$B$3,"Dir=V","Dts=S","Sort=A","Per=M","Fill=P") | K4: =BDH(Universe!B7,Control!$B$5,Control!$B$2,Control!$B$3,"Dir=V","Dts=S","Sort=A","Per=M","Fill=P") | M4: =BDH(Universe!B8,Control!$B$5,Control!$B$2,Control!$B$3,"Dir=V","Dts=S","Sort=A","Per=M","Fill=P") | O4: =BDH(Universe!B9,Control!$B$5,Control!$B$2,Control!$B$3,"Dir=V","Dts=S","Sort=A","Per=M","Fill=P") | Q4: =BDH(Universe!B10,Control!$B$5,Control!$B$2,Control!$B$3,"Dir=V","Dts=S","Sort=A","Per=M","Fill=P") | S4: =BDH(Universe!B11,Control!$B$5,Control!$B$2,Control!$B$3,"Dir=V","Dts=S","Sort=A","Per=M","Fill=P") | U4: =BDH(Universe!B12,Control!$B$5,Control!$B$2,Control!$B$3,"Dir=V","Dts=S","Sort=A","Per=M","Fill=P") | W4: =BDH(Universe!B13,Control!$B$5,Control!$B$2,Control!$B$3,"Dir=V","Dts=S","Sort=A","Per=M","Fill=P") | Y4: =BDH(Universe!B14,Control!$B$5,Control!$B$2,Control!$B$3,"Dir=V","Dts=S","Sort=A","Per=M","Fill=P") | AA4: =BDH(Universe!B15,Control!$B$5,Control!$B$2,Control!$B$3,"Dir=V","Dts=S","Sort=A","Per=M","Fill=P") | AC4: =BDH(Universe!B16,Control!$B$5,Control!$B$2,Control!$B$3,"Dir=V","Dts=S","Sort=A","Per=M","Fill=P") | AE4: =BDH(Universe!B17,Control!$B$5,Control!$B$2,Control!$B$3,"Dir=V","Dts=S","Sort=A","Per=M","Fill=P") | AG4: =BDH(Universe!B18,Control!$B$5,Control!$B$2,Control!$B$3,"Dir=V","Dts=S","Sort=A","Per=M","Fill=P") | AI4: =BDH(Universe!B19,Control!$B$5,Control!$B$2,Control!$B$3,"Dir=V","Dts=S","Sort=A","Per=M","Fill=P") | AK4: =BDH(Universe!B20,Control!$B$5,Control!$B$2,Control!$B$3,"Dir=V","Dts=S","Sort=A","Per=M","Fill=P") | AM4: =BDH(Universe!B21,Control!$B$5,Control!$B$2,Control!$B$3,"Dir=V","Dts=S","Sort=A","Per=M","Fill=P") | AO4: =BDH(Universe!B22,Control!$B$5,Control!$B$2,Control!$B$3,"Dir=V","Dts=S","Sort=A","Per=M","Fill=P") | AQ4: =BDH(Universe!B23,Control!$B$5,Control!$B$2,Control!$B$3,"Dir=V","Dts=S","Sort=A","Per=M","Fill=P") | AS4: =BDH(Universe!B24,Control!$B$5,Control!$B$2,Control!$B$3,"Dir=V","Dts=S","Sort=A","Per=M","Fill=P") | AU4: =BDH(Universe!B25,Control!$B$5,Control!$B$2,Control!$B$3,"Dir=V","Dts=S","Sort=A","Per=M","Fill=P") | AW4: =BDH(Universe!B26,Control!$B$5,Control!$B$2,Control!$B$3,"Dir=V","Dts=S","Sort=A","Per=M","Fill=P") | AY4: =BDH(Universe!B27,Control!$B$5,Control!$B$2,Control!$B$3,"Dir=V","Dts=S","Sort=A","Per=M","Fill=P") | BA4: =BDH(Universe!B28,Control!$B$5,Control!$B$2,Control!$B$3,"Dir=V","Dts=S","Sort=A","Per=M","Fill=P") | BC4: =BDH(Universe!B29,Control!$B$5,Control!$B$2,Control!$B$3,"Dir=V","Dts=S","Sort=A","Per=M","Fill=P") | BE4: =BDH(Universe!B30,Control!$B$5,Control!$B$2,Control!$B$3,"Dir=V","Dts=S","Sort=A","Per=M","Fill=P") | BG4: =BDH(Universe!B31,Control!$B$5,Control!$B$2,Control!$B$3,"Dir=V","Dts=S","Sort=A","Per=M","Fill=P") | BI4: =BDH(Universe!B32,Control!$B$5,Control!$B$2,Control!$B$3,"Dir=V","Dts=S","Sort=A","Per=M","Fill=P") | BK4: =BDH(Universe!B33,Control!$B$5,Control!$B$2,Control!$B$3,"Dir=V","Dts=S","Sort=A","Per=M","Fill=P") | BM4: =BDH(Universe!B34,Control!$B$5,Control!$B$2,Control!$B$3,"Dir=V","Dts=S","Sort=A","Per=M","Fill=P") | BO4: =BDH(Universe!B35,Control!$B$5,Control!$B$2,Control!$B$3,"Dir=V","Dts=S","Sort=A","Per=M","Fill=P") | BQ4: =BDH(Universe!B36,Control!$B$5,Control!$B$2,Control!$B$3,"Dir=V","Dts=S","Sort=A","Per=M","Fill=P") | BS4: =BDH(Universe!B37,Control!$B$5,Control!$B$2,Control!$B$3,"Dir=V","Dts=S","Sort=A","Per=M","Fill=P") | BU4: =BDH(Universe!B38,Control!$B$5,Control!$B$2,Control!$B$3,"Dir=V","Dts=S","Sort=A","Per=M","Fill=P") | BW4: =BDH(Universe!B39,Control!$B$5,Control!$B$2,Control!$B$3,"Dir=V","Dts=S","Sort=A","Per=M","Fill=P") | BY4: =BDH(Universe!B40,Control!$B$5,Control!$B$2,Control!$B$3,"Dir=V","Dts=S","Sort=A","Per=M","Fill=P") | CA4: =BDH(Universe!B41,Control!$B$5,Control!$B$2,Control!$B$3,"Dir=V","Dts=S","Sort=A","Per=M","Fill=P") | CC4: =BDH(Universe!B42,Control!$B$5,Control!$B$2,Control!$B$3,"Dir=V","Dts=S","Sort=A","Per=M","Fill=P") | CE4: =BDH(Universe!B43,Control!$B$5,Control!$B$2,Control!$B$3,"Dir=V","Dts=S","Sort=A","Per=M","Fill=P") | CG4: =BDH(Universe!B44,Control!$B$5,Control!$B$2,Control!$B$3,"Dir=V","Dts=S","Sort=A","Per=M","Fill=P") | CI4: =BDH(Universe!B45,Control!$B$5,Control!$B$2,Control!$B$3,"Dir=V","Dts=S","Sort=A","Per=M","Fill=P") | CK4: =BDH(Universe!B46,Control!$B$5,Control!$B$2,Control!$B$3,"Dir=V","Dts=S","Sort=A","Per=M","Fill=P") | CM4: =BDH(Universe!B47,Control!$B$5,Control!$B$2,Control!$B$3,"Dir=V","Dts=S","Sort=A","Per=M","Fill=P") | CO4: =BDH(Universe!B48,Control!$B$5,Control!$B$2,Control!$B$3,"Dir=V","Dts=S","Sort=A","Per=M","Fill=P") | CQ4: =BDH(Universe!B49,Control!$B$5,Control!$B$2,Control!$B$3,"Dir=V","Dts=S","Sort=A","Per=M","Fill=P") | CS4: =BDH(Universe!B50,Control!$B$5,Control!$B$2,Control!$B$3,"Dir=V","Dts=S","Sort=A","Per=M","Fill=P") | CU4: =BDH(Universe!B51,Control!$B$5,Control!$B$2,Control!$B$3,"Dir=V","Dts=S","Sort=A","Per=M","Fill=P") | CW4: =BDH(Universe!B52,Control!$B$5,Control!$B$2,Control!$B$3,"Dir=V","Dts=S","Sort=A","Per=M","Fill=P") | CY4: =BDH(Universe!B53,Control!$B$5,Control!$B$2,Control!$B$3,"Dir=V","Dts=S","Sort=A","Per=M","Fill=P") | DA4: =BDH(Universe!B54,Control!$B$5,Control!$B$2,Control!$B$3,"Dir=V","Dts=S","Sort=A","Per=M","Fill=P") | DC4: =BDH(Universe!B55,Control!$B$5,Control!$B$2,Control!$B$3,"Dir=V","Dts=S","Sort=A","Per=M","Fill=P") | DE4: =BDH(Universe!B56,Control!$B$5,Control!$B$2,Control!$B$3,"Dir=V","Dts=S","Sort=A","Per=M","Fill=P") | DG4: =BDH(Universe!B57,Control!$B$5,Control!$B$2,Control!$B$3,"Dir=V","Dts=S","Sort=A","Per=M","Fill=P") | DI4: =BDH(Universe!B58,Control!$B$5,Control!$B$2,Control!$B$3,"Dir=V","Dts=S","Sort=A","Per=M","Fill=P") | DK4: =BDH(Universe!B59,Control!$B$5,Control!$B$2,Control!$B$3,"Dir=V","Dts=S","Sort=A","Per=M","Fill=P") | DM4: =BDH(Universe!B60,Control!$B$5,Control!$B$2,Control!$B$3,"Dir=V","Dts=S","Sort=A","Per=M","Fill=P") | DO4: =BDH(Universe!B61,Control!$B$5,Control!$B$2,Control!$B$3,"Dir=V","Dts=S","Sort=A","Per=M","Fill=P") | DQ4: =BDH(Universe!B62,Control!$B$5,Control!$B$2,Control!$B$3,"Dir=V","Dts=S","Sort=A","Per=M","Fill=P") | DS4: =BDH(Universe!B63,Control!$B$5,Control!$B$2,Control!$B$3,"Dir=V","Dts=S","Sort=A","Per=M","Fill=P") | DU4: =BDH(Universe!B64,Control!$B$5,Control!$B$2,Control!$B$3,"Dir=V","Dts=S","Sort=A","Per=M","Fill=P") | DW4: =BDH(Universe!B65,Control!$B$5,Control!$B$2,Control!$B$3,"Dir=V","Dts=S","Sort=A","Per=M","Fill=P") | DY4: =BDH(Universe!B66,Control!$B$5,Control!$B$2,Control!$B$3,"Dir=V","Dts=S","Sort=A","Per=M","Fill=P") | EA4: =BDH(Universe!B67,Control!$B$5,Control!$B$2,Control!$B$3,"Dir=V","Dts=S","Sort=A","Per=M","Fill=P") | EC4: =BDH(Universe!B68,Control!$B$5,Control!$B$2,Control!$B$3,"Dir=V","Dts=S","Sort=A","Per=M","Fill=P") | EE4: =BDH(Universe!B69,Control!$B$5,Control!$B$2,Control!$B$3,"Dir=V","Dts=S","Sort=A","Per=M","Fill=P") | EG4: =BDH(Universe!B70,Control!$B$5,Control!$B$2,Control!$B$3,"Dir=V","Dts=S","Sort=A","Per=M","Fill=P") | EI4: =BDH(Universe!B71,Control!$B$5,Control!$B$2,Control!$B$3,"Dir=V","Dts=S","Sort=A","Per=M","Fill=P") | EK4: =BDH(Universe!B72,Control!$B$5,Control!$B$2,Control!$B$3,"Dir=V","Dts=S","Sort=A","Per=M","Fill=P") | EM4: =BDH(Universe!B73,Control!$B$5,Control!$B$2,Control!$B$3,"Dir=V","Dts=S","Sort=A","Per=M","Fill=P") | EO4: =BDH(Universe!B74,Control!$B$5,Control!$B$2,Control!$B$3,"Dir=V","Dts=S","Sort=A","Per=M","Fill=P") | EQ4: =BDH(Universe!B75,Control!$B$5,Control!$B$2,Control!$B$3,"Dir=V","Dts=S","Sort=A","Per=M","Fill=P") | ES4: =BDH(Universe!B76,Control!$B$5,Control!$B$2,Control!$B$3,"Dir=V","Dts=S","Sort=A","Per=M","Fill=P") | EU4: =BDH(Universe!B77,Control!$B$5,Control!$B$2,Control!$B$3,"Dir=V","Dts=S","Sort=A","Per=M","Fill=P") | EW4: =BDH(Universe!B78,Control!$B$5,Control!$B$2,Control!$B$3,"Dir=V","Dts=S","Sort=A","Per=M","Fill=P") | EY4: =BDH(Universe!B79,Control!$B$5,Control!$B$2,Control!$B$3,"Dir=V","Dts=S","Sort=A","Per=M","Fill=P") | FA4: =BDH(Universe!B80,Control!$B$5,Control!$B$2,Control!$B$3,"Dir=V","Dts=S","Sort=A","Per=M","Fill=P")

Sheet Book_Index
A1: YahooTicker | B1: BloombergTicker | C1: StartCol | D1: ExcelCol | E1: BDH_Cell
A2: D05.SI | B2: D05 SP Equity | C2: 1 | D2: A | E2: A4
A3: O39.SI | B3: O39 SP Equity | C3: 3 | D3: C | E3: C4
A4: Z74.SI | B4: Z74 SP Equity | C4: 5 | D4: E | E4: E4
A5: U11.SI | B5: U11 SP Equity | C5: 7 | D5: G | E5: G4
A6: S63.SI | B6: S63 SP Equity | C6: 9 | D6: I | E6: I4
A7: S68.SI | B7: S68 SP Equity | C7: 11 | D7: K | E7: K4
A8: J36.SI | B8: J36 SP Equity | C8: 13 | D8: M | E8: M4
A9: C6L.SI | B9: C6L SP Equity | C9: 15 | D9: O | E9: O4
A10: F34.SI | B10: F34 SP Equity | C10: 17 | D10: Q | E10: Q4
A11: H78.SI | B11: H78 SP Equity | C11: 19 | D11: S | E11: S4
A12: BN4.SI | B12: BN4 SP Equity | C12: 21 | D12: U | E12: U4
A13: C38U.SI | B13: C38U SP Equity | C13: 23 | D13: W | E13: W4
... A80: DCRU.SI | B80: DCRU SP Equity | C80: 157 | D80: FA | E80: FA4

Sheet Book_Notes
A1: Book sheet notes
A2: WHY YOU SAW 'Enumeration Error' WITH BQ:
A3: Bloomberg BDH periodicity must be D / W / M / Q / Y (or CQ / FY etc.).
A4: 'BQ' is NOT valid → Enumeration Error. This template now uses Per=M.
A6: DATES: every ticker has its own Date column (Dts=S), not only DBS.
A7: Field: BOOK_VAL_PER_SH, Period: M (monthly).
A8: See Book_Index for column map. bbg_to_csv.py merges blocks → book_data.csv.
A9: Fundamentals may only update quarterly; monthly series can repeat last report.

Sheet Categories
A1: Ticker | B1: sector | C1: market_cap
A2: D05.SI | B2: =BDP(Universe!B2,"GICS_SECTOR_NAME") | C2: =BDP(Universe!B2,"CUR_MKT_CAP")
A3: O39.SI | B3: =BDP(Universe!B3,"GICS_SECTOR_NAME") | C3: =BDP(Universe!B3,"CUR_MKT_CAP")
A4: Z74.SI | B4: =BDP(Universe!B4,"GICS_SECTOR_NAME") | C4: =BDP(Universe!B4,"CUR_MKT_CAP")
A5: U11.SI | B5: =BDP(Universe!B5,"GICS_SECTOR_NAME") | C5: =BDP(Universe!B5,"CUR_MKT_CAP")
A6: S63.SI | B6: =BDP(Universe!B6,"GICS_SECTOR_NAME") | C6: =BDP(Universe!B6,"CUR_MKT_CAP")
A7: S68.SI | B7: =BDP(Universe!B7,"GICS_SECTOR_NAME") | C7: =BDP(Universe!B7,"CUR_MKT_CAP")
A8: J36.SI | B8: =BDP(Universe!B8,"GICS_SECTOR_NAME") | C8: =BDP(Universe!B8,"CUR_MKT_CAP")
A9: C6L.SI | B9: =BDP(Universe!B9,"GICS_SECTOR_NAME") | C9: =BDP(Universe!B9,"CUR_MKT_CAP")
A10: F34.SI | B10: =BDP(Universe!B10,"GICS_SECTOR_NAME") | C10: =BDP(Universe!B10,"CUR_MKT_CAP")
A11: H78.SI | B11: =BDP(Universe!B11,"GICS_SECTOR_NAME") | C11: =BDP(Universe!B11,"CUR_MKT_CAP")
A12: BN4.SI | B12: =BDP(Universe!B12,"GICS_SECTOR_NAME") | C12: =BDP(Universe!B12,"CUR_MKT_CAP")
A13: C38U.SI | B13: =BDP(Universe!B13,"GICS_SECTOR_NAME") | C13: =BDP(Universe!B13,"CUR_MKT_CAP")
... A80: DCRU.SI | B80: =BDP(Universe!B80,"GICS_SECTOR_NAME") | C80: =BDP(Universe!B80,"CUR_MKT_CAP")

Sheet Categories_Notes
A1: Categories notes
A2: Export this sheet as categorizations_data.csv (headers: Ticker,sector,market_cap).
A3: If GICS_SECTOR_NAME is empty, switch formula to INDUSTRY_SECTOR or CLASSIFICATION_LEVEL_1_NAME.
A4: market_cap should be absolute CUR_MKT_CAP (same units across names).

Sheet Dividends
A1: DVD_HIST_ALL (BDS) — one block per ticker. Row3=Yahoo ticker, Row4=BDS formula. Refresh Bloomberg, then run bbg_to_csv.py
A3: D05.SI | I3: O39.SI | Q3: Z74.SI | Y3: U11.SI | AG3: S63.SI | AO3: S68.SI | AW3: J36.SI | BE3: C6L.SI | BM3: F34.SI | BU3: H78.SI | CC3: BN4.SI | CK3: C38U.SI | CS3: U14.SI | DA3: 5E2.SI | DI3: G13.SI | DQ3: S58.SI | DY3: N2IU.SI | EG3: C09.SI | EO3: D01.SI | EW3: M44U.SI | FE3: EB5.SI | FM3: ME8U.SI | FU3: AJBU.SI | GC3: VC2.SI | GK3: U06.SI | GS3: OV8.SI | HA3: V03.SI | HI3: J69U.SI | HQ3: T82U.SI | HY3: K71U.SI | IG3: U10.SI | IO3: TQ5.SI | IW3: CJL.SI | JE3: BUOU.SI | JM3: S59.SI | JU3: E5H.SI | KC3: H02.SI | KK3: HMN.SI | KS3: A7RU.SI | LA3: P8Z.SI | LI3: C52.SI | LQ3: AWX.SI | LY3: AIY.SI | MG3: C2PU.SI | MO3: F17.SI | MW3: H15.SI | NE3: H22.SI | NM3: 558.SI | NU3: NS8U.SI | OC3: 8Y.SI | OK3: F99.SI | OS3: TS0U.SI | PA3: 9A4U.SI | PI3: 8C8U.SI | PQ3: SEB.SI | PY3: Z25.SI | QG3: AP4.SI | QO3: P40U.SI | QW3: B61.SI | RE3: NTDU.SI | RM3: W05.SI | RU3: Q5T.SI | SC3: BEC.SI | SK3: E28.SI | SS3: UIBU.SI | TA3: AU8U.SI | TI3: P52.SI | TQ3: S41.SI | TY3: S61.SI | UG3: PCT.SI | UO3: ADN.SI | UW3: F9D.SI | VE3: FHH.SI | VM3: J85.SI | VU3: T6I.SI | WC3: RE4.SI | WK3: 544.SI | WS3: CRPU.SI | XA3: DCRU.SI
A4: =BDS(Universe!B2,Control!$B$8,"Headers=Y","DVD_START_DT="&TEXT(Control!$B$2,"yyyymmdd"),"DVD_END_DT="&TEXT(Control!$B$3,"yyyymmdd")) | I4: =BDS(Universe!B3,Control!$B$8,"Headers=Y","DVD_START_DT="&TEXT(Control!$B$2,"yyyymmdd"),"DVD_END_DT="&TEXT(Control!$B$3,"yyyymmdd")) | Q4: =BDS(Universe!B4,Control!$B$8,"Headers=Y","DVD_START_DT="&TEXT(Control!$B$2,"yyyymmdd"),"DVD_END_DT="&TEXT(Control!$B$3,"yyyymmdd")) | Y4: =BDS(Universe!B5,Control!$B$8,"Headers=Y","DVD_START_DT="&TEXT(Control!$B$2,"yyyymmdd"),"DVD_END_DT="&TEXT(Control!$B$3,"yyyymmdd")) | AG4: =BDS(Universe!B6,Control!$B$8,"Headers=Y","DVD_START_DT="&TEXT(Control!$B$2,"yyyymmdd"),"DVD_END_DT="&TEXT(Control!$B$3,"yyyymmdd")) | AO4: =BDS(Universe!B7,Control!$B$8,"Headers=Y","DVD_START_DT="&TEXT(Control!$B$2,"yyyymmdd"),"DVD_END_DT="&TEXT(Control!$B$3,"yyyymmdd")) | AW4: =BDS(Universe!B8,Control!$B$8,"Headers=Y","DVD_START_DT="&TEXT(Control!$B$2,"yyyymmdd"),"DVD_END_DT="&TEXT(Control!$B$3,"yyyymmdd")) | BE4: =BDS(Universe!B9,Control!$B$8,"Headers=Y","DVD_START_DT="&TEXT(Control!$B$2,"yyyymmdd"),"DVD_END_DT="&TEXT(Control!$B$3,"yyyymmdd")) | BM4: =BDS(Universe!B10,Control!$B$8,"Headers=Y","DVD_START_DT="&TEXT(Control!$B$2,"yyyymmdd"),"DVD_END_DT="&TEXT(Control!$B$3,"yyyymmdd")) | BU4: =BDS(Universe!B11,Control!$B$8,"Headers=Y","DVD_START_DT="&TEXT(Control!$B$2,"yyyymmdd"),"DVD_END_DT="&TEXT(Control!$B$3,"yyyymmdd")) | CC4: =BDS(Universe!B12,Control!$B$8,"Headers=Y","DVD_START_DT="&TEXT(Control!$B$2,"yyyymmdd"),"DVD_END_DT="&TEXT(Control!$B$3,"yyyymmdd")) | CK4: =BDS(Universe!B13,Control!$B$8,"Headers=Y","DVD_START_DT="&TEXT(Control!$B$2,"yyyymmdd"),"DVD_END_DT="&TEXT(Control!$B$3,"yyyymmdd")) | CS4: =BDS(Universe!B14,Control!$B$8,"Headers=Y","DVD_START_DT="&TEXT(Control!$B$2,"yyyymmdd"),"DVD_END_DT="&TEXT(Control!$B$3,"yyyymmdd")) | DA4: =BDS(Universe!B15,Control!$B$8,"Headers=Y","DVD_START_DT="&TEXT(Control!$B$2,"yyyymmdd"),"DVD_END_DT="&TEXT(Control!$B$3,"yyyymmdd")) | DI4: =BDS(Universe!B16,Control!$B$8,"Headers=Y","DVD_START_DT="&TEXT(Control!$B$2,"yyyymmdd"),"DVD_END_DT="&TEXT(Control!$B$3,"yyyymmdd")) | DQ4: =BDS(Universe!B17,Control!$B$8,"Headers=Y","DVD_START_DT="&TEXT(Control!$B$2,"yyyymmdd"),"DVD_END_DT="&TEXT(Control!$B$3,"yyyymmdd")) | DY4: =BDS(Universe!B18,Control!$B$8,"Headers=Y","DVD_START_DT="&TEXT(Control!$B$2,"yyyymmdd"),"DVD_END_DT="&TEXT(Control!$B$3,"yyyymmdd")) | EG4: =BDS(Universe!B19,Control!$B$8,"Headers=Y","DVD_START_DT="&TEXT(Control!$B$2,"yyyymmdd"),"DVD_END_DT="&TEXT(Control!$B$3,"yyyymmdd")) | EO4: =BDS(Universe!B20,Control!$B$8,"Headers=Y","DVD_START_DT="&TEXT(Control!$B$2,"yyyymmdd"),"DVD_END_DT="&TEXT(Control!$B$3,"yyyymmdd")) | EW4: =BDS(Universe!B21,Control!$B$8,"Headers=Y","DVD_START_DT="&TEXT(Control!$B$2,"yyyymmdd"),"DVD_END_DT="&TEXT(Control!$B$3,"yyyymmdd")) | FE4: =BDS(Universe!B22,Control!$B$8,"Headers=Y","DVD_START_DT="&TEXT(Control!$B$2,"yyyymmdd"),"DVD_END_DT="&TEXT(Control!$B$3,"yyyymmdd")) | FM4: =BDS(Universe!B23,Control!$B$8,"Headers=Y","DVD_START_DT="&TEXT(Control!$B$2,"yyyymmdd"),"DVD_END_DT="&TEXT(Control!$B$3,"yyyymmdd")) | FU4: =BDS(Universe!B24,Control!$B$8,"Headers=Y","DVD_START_DT="&TEXT(Control!$B$2,"yyyymmdd"),"DVD_END_DT="&TEXT(Control!$B$3,"yyyymmdd")) | GC4: =BDS(Universe!B25,Control!$B$8,"Headers=Y","DVD_START_DT="&TEXT(Control!$B$2,"yyyymmdd"),"DVD_END_DT="&TEXT(Control!$B$3,"yyyymmdd")) | GK4: =BDS(Universe!B26,Control!$B$8,"Headers=Y","DVD_START_DT="&TEXT(Control!$B$2,"yyyymmdd"),"DVD_END_DT="&TEXT(Control!$B$3,"yyyymmdd")) | GS4: =BDS(Universe!B27,Control!$B$8,"Headers=Y","DVD_START_DT="&TEXT(Control!$B$2,"yyyymmdd"),"DVD_END_DT="&TEXT(Control!$B$3,"yyyymmdd")) | HA4: =BDS(Universe!B28,Control!$B$8,"Headers=Y","DVD_START_DT="&TEXT(Control!$B$2,"yyyymmdd"),"DVD_END_DT="&TEXT(Control!$B$3,"yyyymmdd")) | HI4: =BDS(Universe!B29,Control!$B$8,"Headers=Y","DVD_START_DT="&TEXT(Control!$B$2,"yyyymmdd"),"DVD_END_DT="&TEXT(Control!$B$3,"yyyymmdd")) | HQ4: =BDS(Universe!B30,Control!$B$8,"Headers=Y","DVD_START_DT="&TEXT(Control!$B$2,"yyyymmdd"),"DVD_END_DT="&TEXT(Control!$B$3,"yyyymmdd")) | HY4: =BDS(Universe!B31,Control!$B$8,"Headers=Y","DVD_START_DT="&TEXT(Control!$B$2,"yyyymmdd"),"DVD_END_DT="&TEXT(Control!$B$3,"yyyymmdd")) | IG4: =BDS(Universe!B32,Control!$B$8,"Headers=Y","DVD_START_DT="&TEXT(Control!$B$2,"yyyymmdd"),"DVD_END_DT="&TEXT(Control!$B$3,"yyyymmdd")) | IO4: =BDS(Universe!B33,Control!$B$8,"Headers=Y","DVD_START_DT="&TEXT(Control!$B$2,"yyyymmdd"),"DVD_END_DT="&TEXT(Control!$B$3,"yyyymmdd")) | IW4: =BDS(Universe!B34,Control!$B$8,"Headers=Y","DVD_START_DT="&TEXT(Control!$B$2,"yyyymmdd"),"DVD_END_DT="&TEXT(Control!$B$3,"yyyymmdd")) | JE4: =BDS(Universe!B35,Control!$B$8,"Headers=Y","DVD_START_DT="&TEXT(Control!$B$2,"yyyymmdd"),"DVD_END_DT="&TEXT(Control!$B$3,"yyyymmdd")) | JM4: =BDS(Universe!B36,Control!$B$8,"Headers=Y","DVD_START_DT="&TEXT(Control!$B$2,"yyyymmdd"),"DVD_END_DT="&TEXT(Control!$B$3,"yyyymmdd")) | JU4: =BDS(Universe!B37,Control!$B$8,"Headers=Y","DVD_START_DT="&TEXT(Control!$B$2,"yyyymmdd"),"DVD_END_DT="&TEXT(Control!$B$3,"yyyymmdd")) | KC4: =BDS(Universe!B38,Control!$B$8,"Headers=Y","DVD_START_DT="&TEXT(Control!$B$2,"yyyymmdd"),"DVD_END_DT="&TEXT(Control!$B$3,"yyyymmdd")) | KK4: =BDS(Universe!B39,Control!$B$8,"Headers=Y","DVD_START_DT="&TEXT(Control!$B$2,"yyyymmdd"),"DVD_END_DT="&TEXT(Control!$B$3,"yyyymmdd")) | KS4: =BDS(Universe!B40,Control!$B$8,"Headers=Y","DVD_START_DT="&TEXT(Control!$B$2,"yyyymmdd"),"DVD_END_DT="&TEXT(Control!$B$3,"yyyymmdd")) | LA4: =BDS(Universe!B41,Control!$B$8,"Headers=Y","DVD_START_DT="&TEXT(Control!$B$2,"yyyymmdd"),"DVD_END_DT="&TEXT(Control!$B$3,"yyyymmdd")) | LI4: =BDS(Universe!B42,Control!$B$8,"Headers=Y","DVD_START_DT="&TEXT(Control!$B$2,"yyyymmdd"),"DVD_END_DT="&TEXT(Control!$B$3,"yyyymmdd")) | LQ4: =BDS(Universe!B43,Control!$B$8,"Headers=Y","DVD_START_DT="&TEXT(Control!$B$2,"yyyymmdd"),"DVD_END_DT="&TEXT(Control!$B$3,"yyyymmdd")) | LY4: =BDS(Universe!B44,Control!$B$8,"Headers=Y","DVD_START_DT="&TEXT(Control!$B$2,"yyyymmdd"),"DVD_END_DT="&TEXT(Control!$B$3,"yyyymmdd")) | MG4: =BDS(Universe!B45,Control!$B$8,"Headers=Y","DVD_START_DT="&TEXT(Control!$B$2,"yyyymmdd"),"DVD_END_DT="&TEXT(Control!$B$3,"yyyymmdd")) | MO4: =BDS(Universe!B46,Control!$B$8,"Headers=Y","DVD_START_DT="&TEXT(Control!$B$2,"yyyymmdd"),"DVD_END_DT="&TEXT(Control!$B$3,"yyyymmdd")) | MW4: =BDS(Universe!B47,Control!$B$8,"Headers=Y","DVD_START_DT="&TEXT(Control!$B$2,"yyyymmdd"),"DVD_END_DT="&TEXT(Control!$B$3,"yyyymmdd")) | NE4: =BDS(Universe!B48,Control!$B$8,"Headers=Y","DVD_START_DT="&TEXT(Control!$B$2,"yyyymmdd"),"DVD_END_DT="&TEXT(Control!$B$3,"yyyymmdd")) | NM4: =BDS(Universe!B49,Control!$B$8,"Headers=Y","DVD_START_DT="&TEXT(Control!$B$2,"yyyymmdd"),"DVD_END_DT="&TEXT(Control!$B$3,"yyyymmdd")) | NU4: =BDS(Universe!B50,Control!$B$8,"Headers=Y","DVD_START_DT="&TEXT(Control!$B$2,"yyyymmdd"),"DVD_END_DT="&TEXT(Control!$B$3,"yyyymmdd")) | OC4: =BDS(Universe!B51,Control!$B$8,"Headers=Y","DVD_START_DT="&TEXT(Control!$B$2,"yyyymmdd"),"DVD_END_DT="&TEXT(Control!$B$3,"yyyymmdd")) | OK4: =BDS(Universe!B52,Control!$B$8,"Headers=Y","DVD_START_DT="&TEXT(Control!$B$2,"yyyymmdd"),"DVD_END_DT="&TEXT(Control!$B$3,"yyyymmdd")) | OS4: =BDS(Universe!B53,Control!$B$8,"Headers=Y","DVD_START_DT="&TEXT(Control!$B$2,"yyyymmdd"),"DVD_END_DT="&TEXT(Control!$B$3,"yyyymmdd")) | PA4: =BDS(Universe!B54,Control!$B$8,"Headers=Y","DVD_START_DT="&TEXT(Control!$B$2,"yyyymmdd"),"DVD_END_DT="&TEXT(Control!$B$3,"yyyymmdd")) | PI4: =BDS(Universe!B55,Control!$B$8,"Headers=Y","DVD_START_DT="&TEXT(Control!$B$2,"yyyymmdd"),"DVD_END_DT="&TEXT(Control!$B$3,"yyyymmdd")) | PQ4: =BDS(Universe!B56,Control!$B$8,"Headers=Y","DVD_START_DT="&TEXT(Control!$B$2,"yyyymmdd"),"DVD_END_DT="&TEXT(Control!$B$3,"yyyymmdd")) | PY4: =BDS(Universe!B57,Control!$B$8,"Headers=Y","DVD_START_DT="&TEXT(Control!$B$2,"yyyymmdd"),"DVD_END_DT="&TEXT(Control!$B$3,"yyyymmdd")) | QG4: =BDS(Universe!B58,Control!$B$8,"Headers=Y","DVD_START_DT="&TEXT(Control!$B$2,"yyyymmdd"),"DVD_END_DT="&TEXT(Control!$B$3,"yyyymmdd")) | QO4: =BDS(Universe!B59,Control!$B$8,"Headers=Y","DVD_START_DT="&TEXT(Control!$B$2,"yyyymmdd"),"DVD_END_DT="&TEXT(Control!$B$3,"yyyymmdd")) | QW4: =BDS(Universe!B60,Control!$B$8,"Headers=Y","DVD_START_DT="&TEXT(Control!$B$2,"yyyymmdd"),"DVD_END_DT="&TEXT(Control!$B$3,"yyyymmdd")) | RE4: =BDS(Universe!B61,Control!$B$8,"Headers=Y","DVD_START_DT="&TEXT(Control!$B$2,"yyyymmdd"),"DVD_END_DT="&TEXT(Control!$B$3,"yyyymmdd")) | RM4: =BDS(Universe!B62,Control!$B$8,"Headers=Y","DVD_START_DT="&TEXT(Control!$B$2,"yyyymmdd"),"DVD_END_DT="&TEXT(Control!$B$3,"yyyymmdd")) | RU4: =BDS(Universe!B63,Control!$B$8,"Headers=Y","DVD_START_DT="&TEXT(Control!$B$2,"yyyymmdd"),"DVD_END_DT="&TEXT(Control!$B$3,"yyyymmdd")) | SC4: =BDS(Universe!B64,Control!$B$8,"Headers=Y","DVD_START_DT="&TEXT(Control!$B$2,"yyyymmdd"),"DVD_END_DT="&TEXT(Control!$B$3,"yyyymmdd")) | SK4: =BDS(Universe!B65,Control!$B$8,"Headers=Y","DVD_START_DT="&TEXT(Control!$B$2,"yyyymmdd"),"DVD_END_DT="&TEXT(Control!$B$3,"yyyymmdd")) | SS4: =BDS(Universe!B66,Control!$B$8,"Headers=Y","DVD_START_DT="&TEXT(Control!$B$2,"yyyymmdd"),"DVD_END_DT="&TEXT(Control!$B$3,"yyyymmdd")) | TA4: =BDS(Universe!B67,Control!$B$8,"Headers=Y","DVD_START_DT="&TEXT(Control!$B$2,"yyyymmdd"),"DVD_END_DT="&TEXT(Control!$B$3,"yyyymmdd")) | TI4: =BDS(Universe!B68,Control!$B$8,"Headers=Y","DVD_START_DT="&TEXT(Control!$B$2,"yyyymmdd"),"DVD_END_DT="&TEXT(Control!$B$3,"yyyymmdd")) | TQ4: =BDS(Universe!B69,Control!$B$8,"Headers=Y","DVD_START_DT="&TEXT(Control!$B$2,"yyyymmdd"),"DVD_END_DT="&TEXT(Control!$B$3,"yyyymmdd")) | TY4: =BDS(Universe!B70,Control!$B$8,"Headers=Y","DVD_START_DT="&TEXT(Control!$B$2,"yyyymmdd"),"DVD_END_DT="&TEXT(Control!$B$3,"yyyymmdd")) | UG4: =BDS(Universe!B71,Control!$B$8,"Headers=Y","DVD_START_DT="&TEXT(Control!$B$2,"yyyymmdd"),"DVD_END_DT="&TEXT(Control!$B$3,"yyyymmdd")) | UO4: =BDS(Universe!B72,Control!$B$8,"Headers=Y","DVD_START_DT="&TEXT(Control!$B$2,"yyyymmdd"),"DVD_END_DT="&TEXT(Control!$B$3,"yyyymmdd")) | UW4: =BDS(Universe!B73,Control!$B$8,"Headers=Y","DVD_START_DT="&TEXT(Control!$B$2,"yyyymmdd"),"DVD_END_DT="&TEXT(Control!$B$3,"yyyymmdd")) | VE4: =BDS(Universe!B74,Control!$B$8,"Headers=Y","DVD_START_DT="&TEXT(Control!$B$2,"yyyymmdd"),"DVD_END_DT="&TEXT(Control!$B$3,"yyyymmdd")) | VM4: =BDS(Universe!B75,Control!$B$8,"Headers=Y","DVD_START_DT="&TEXT(Control!$B$2,"yyyymmdd"),"DVD_END_DT="&TEXT(Control!$B$3,"yyyymmdd")) | VU4: =BDS(Universe!B76,Control!$B$8,"Headers=Y","DVD_START_DT="&TEXT(Control!$B$2,"yyyymmdd"),"DVD_END_DT="&TEXT(Control!$B$3,"yyyymmdd")) | WC4: =BDS(Universe!B77,Control!$B$8,"Headers=Y","DVD_START_DT="&TEXT(Control!$B$2,"yyyymmdd"),"DVD_END_DT="&TEXT(Control!$B$3,"yyyymmdd")) | WK4: =BDS(Universe!B78,Control!$B$8,"Headers=Y","DVD_START_DT="&TEXT(Control!$B$2,"yyyymmdd"),"DVD_END_DT="&TEXT(Control!$B$3,"yyyymmdd")) | WS4: =BDS(Universe!B79,Control!$B$8,"Headers=Y","DVD_START_DT="&TEXT(Control!$B$2,"yyyymmdd"),"DVD_END_DT="&TEXT(Control!$B$3,"yyyymmdd")) | XA4: =BDS(Universe!B80,Control!$B$8,"Headers=Y","DVD_START_DT="&TEXT(Control!$B$2,"yyyymmdd"),"DVD_END_DT="&TEXT(Control!$B$3,"yyyymmdd"))

Sheet Dividends_Index
A1: YahooTicker | B1: BloombergTicker | C1: StartCol | D1: ExcelCol | E1: BDS_Cell
A2: D05.SI | B2: D05 SP Equity | C2: 1 | D2: A | E2: A4
A3: O39.SI | B3: O39 SP Equity | C3: 9 | D3: I | E3: I4
A4: Z74.SI | B4: Z74 SP Equity | C4: 17 | D4: Q | E4: Q4
A5: U11.SI | B5: U11 SP Equity | C5: 25 | D5: Y | E5: Y4
A6: S63.SI | B6: S63 SP Equity | C6: 33 | D6: AG | E6: AG4
A7: S68.SI | B7: S68 SP Equity | C7: 41 | D7: AO | E7: AO4
A8: J36.SI | B8: J36 SP Equity | C8: 49 | D8: AW | E8: AW4
A9: C6L.SI | B9: C6L SP Equity | C9: 57 | D9: BE | E9: BE4
A10: F34.SI | B10: F34 SP Equity | C10: 65 | D10: BM | E10: BM4
A11: H78.SI | B11: H78 SP Equity | C11: 73 | D11: BU | E11: BU4
A12: BN4.SI | B12: BN4 SP Equity | C12: 81 | D12: CC | E12: CC4
A13: C38U.SI | B13: C38U SP Equity | C13: 89 | D13: CK | E13: CK4
... A80: DCRU.SI | B80: DCRU SP Equity | C80: 625 | D80: XA | E80: XA4

Sheet Dividends_Notes
A1: Dividends use Bloomberg DVD_HIST (BDS DVD_HIST_ALL)
A3: Function: BDS(security, "DVD_HIST_ALL", "Headers=Y", DVD_START_DT, DVD_END_DT)
A4: Date overrides MUST be DVD_START_DT / DVD_END_DT (yyyymmdd).
A5: Do NOT use StartDateTime / EndDateTime — those cause: Invalid override field: EndDateTime.
A6: Control!B8 = DVD_HIST_ALL (or DVD_HIST if your terminal prefers that field).
A8: Layout:
A9: • Dividends sheet: each ticker owns 8 columns (side-by-side) so histories do not clash.
A10: • Row 3 = Yahoo ticker label (D05.SI, O39.SI, …) — NOT only DBS.
A11: • Row 4 = BDS formula; spill shows Ex-Date, Dividend Amount, Dividend Type, …
A12: • Dividends_Index lists every ticker and its starting column.
A14: Special dividends:
A15: DVD_HIST lists Type = Regular / Interim / Final / Special / Stock separately.
... A19: After refresh: python bloomberg/bbg_to_csv.py --xlsx bloomberg/SG_Bloomberg_Historical_Pull.xlsx

Sheet Dividends_Detail
A1: Optional: one-ticker DVD_HIST_ALL — inspect Special vs Regular
A3: SelectYahoo | B3: D05.SI | C3: ← change me (e.g. O39.SI). Default D05.SI is DBS only as an example.
A4: BloombergTicker | B4: =IFERROR(INDEX(Universe!B:B,MATCH(B3,Universe!A:A,0)),"")
A6: BDS DVD_HIST_ALL (spills below)
A7: =BDS(B4,Control!$B$8,"Headers=Y","DVD_START_DT="&TEXT(Control!$B$2,"yyyymmdd"),"DVD_END_DT="&TEXT(Control!$B$3,"yyyymmdd"))
A9: After refresh, point these SUMIFs at your Amount and Type columns in the spill:
A10: Sum ALL amounts (example B8:B500): | B10: =IFERROR(SUM(B8:B500),0)
A11: Sum Ordinary (Regular/Interim/Final): | B11: =IFERROR(SUMIF(C8:C500,"*Regular*",B8:B500)+SUMIF(C8:C500,"*Interim*",B8:B500)+SUMIF(C8:C500,"*Final*",B8:B500),0)
A12: Sum Special only: | B12: =IFERROR(SUMIF(C8:C500,"*Special*",B8:B500),0)
A14: Adjust column letters to match your BDS spill (Amount / Type).

Sheet FAQ
A1: FAQ — Book BQ error / Dividends Special / Only DBS dates
A3: 1) Book value Enumeration Error and BQ
A4: Cause: Per=BQ is invalid in Bloomberg BDH.
A5: Fix: use Per=M (monthly) or Per=Q (quarterly). Never BQ.
A7: 2) Dividend history — use DVD_HIST (BDS DVD_HIST_ALL)
A8: Overrides: DVD_START_DT / DVD_END_DT (yyyymmdd). Never EndDateTime.
A9: Dividends sheet has one BDS block per ticker (see Dividends_Index).
A10: Special = dividend type line, not a sum. Use Dividends_Detail SUMIF for totals.
A12: 3) Why only DBS dates before?
A13: Old Prices/Book used Dts=S only on first ticker (D05.SI / DBS).
A14: Now EVERY ticker has its own Date|Value block (Dts=S). Scroll right / see Index sheets.

Sheet Export_Checklist
A1: Export checklist → data/sg/raw/
A3: After all sheets show numbers (not #N/A Requesting Data...):
A5: Option A — Automated (recommended)
A6: 1. Save this workbook (formulas calculated / values cached).
A7: 2. Confirm Prices/Book: each ticker has its own Date column (scroll right).
A8: 3. Refresh Dividends (DVD_HIST_ALL blocks).
A9: 4. Run:
A10: python bloomberg/bbg_to_csv.py --xlsx bloomberg/SG_Bloomberg_Historical_Pull.xlsx
A11: 5. Confirm data/sg/raw/*.csv then: python main.py --market sg --skip-download
A13: Validation
A14: • Prices/Book: per-ticker Date|Value blocks (not DBS-only dates)
A15: • Dividends: BDS DVD_HIST_ALL + DVD_START_DT / DVD_END_DT
A16: • Book: Per=M
