Workbook

Sheet README
A1: SG Bloomberg Historical Pull — Quant Trading
A3: Purpose
A4: Pull SGX history from Bloomberg into the 4 CSV layouts this project needs under data/sg/raw/, then run: python main.py --market sg --skip-download
A6: Sheets
A7: 1. Control — start/end dates and pull settings (edit these first)
A8: 2. Universe — Yahoo .SI tickers ↔ Bloomberg SP Equity codes
A9: 3. Prices — daily adjusted PX_LAST (→ price_data.csv)
A10: 4. Book — quarterly BOOK_VAL_PER_SH (→ book_data.csv)
A11: 5. Categories — sector + market cap BDP (→ categorizations_data.csv)
A12: 6. Dividends — per-ticker DVD_HIST pull helper (→ dividend_data.csv)
A13: 7. Export_Checklist — save-as-CSV steps
A15: How to refresh (Bloomberg Terminal PC)
... A30: TA-Lib / OHLCV not required — this project uses adjusted close only.

Sheet Control
A1: Parameter | B1: Value
A2: StartDate | B2: =EDATE(TODAY(),-60) -> 44444 | C2: Rolling 5 years (60 months). Hardcode e.g. 2021-09-01 to match config if preferred.
A3: EndDate | B3: =TODAY()-1 -> 46269 | C3: Leave as TODAY()-1 or hardcode e.g. 2026-09-04
A4: PriceField | B4: PX_LAST | C4: Adjusted via BDH overrides on Prices sheet
A5: BookField | B5: BOOK_VAL_PER_SH | C5: Quarterly book value per share
A6: BookPeriod | B6: BQ | C6: Bloomberg quarterly periodicity
A7: PricePeriod | B7: D | C7: Daily
A8: Currency | B8: SGD | C8: Informational
A9: Exchange | B9: SP / SGX | C9: Bloomberg yellow-key Equity, SGX
A10: OutputFolder | B10: C:\Users\taiji\Desktop\Python Project\Quant Learning Journey\quant-trading\data\sg\raw | C10: Where CSVs should land
A12: BDH price overrides (already embedded in Prices formulas)
A13: CshAdjNormal=Y | CshAdjAbnormal=Y | CapChg=Y | Dir=V | Dts=S | Sort=A | Fill=P | Days=A

Sheet Universe
A1: YahooTicker | B1: BloombergTicker | C1: Include | D1: Name_BDP | E1: Last_BDP | F1: Sector_BDP | G1: MktCap_BDP
A2: D05.SI | B2: D05 SP Equity | C2: YES | D2: =BDP(B2,"NAME") -> #NAME? | E2: =BDP(B2,"PX_LAST") -> #NAME? | F2: =BDP(B2,"GICS_SECTOR_NAME") -> #NAME? | G2: =BDP(B2,"CUR_MKT_CAP") -> #NAME?
A3: O39.SI | B3: O39 SP Equity | C3: YES | D3: =BDP(B3,"NAME") -> #NAME? | E3: =BDP(B3,"PX_LAST") -> #NAME? | F3: =BDP(B3,"GICS_SECTOR_NAME") -> #NAME? | G3: =BDP(B3,"CUR_MKT_CAP") -> #NAME?
A4: Z74.SI | B4: Z74 SP Equity | C4: YES | D4: =BDP(B4,"NAME") -> #NAME? | E4: =BDP(B4,"PX_LAST") -> #NAME? | F4: =BDP(B4,"GICS_SECTOR_NAME") -> #NAME? | G4: =BDP(B4,"CUR_MKT_CAP") -> #NAME?
A5: U11.SI | B5: U11 SP Equity | C5: YES | D5: =BDP(B5,"NAME") -> #NAME? | E5: =BDP(B5,"PX_LAST") -> #NAME? | F5: =BDP(B5,"GICS_SECTOR_NAME") -> #NAME? | G5: =BDP(B5,"CUR_MKT_CAP") -> #NAME?
A6: S63.SI | B6: S63 SP Equity | C6: YES | D6: =BDP(B6,"NAME") -> #NAME? | E6: =BDP(B6,"PX_LAST") -> #NAME? | F6: =BDP(B6,"GICS_SECTOR_NAME") -> #NAME? | G6: =BDP(B6,"CUR_MKT_CAP") -> #NAME?
A7: S68.SI | B7: S68 SP Equity | C7: YES | D7: =BDP(B7,"NAME") -> #NAME? | E7: =BDP(B7,"PX_LAST") -> #NAME? | F7: =BDP(B7,"GICS_SECTOR_NAME") -> #NAME? | G7: =BDP(B7,"CUR_MKT_CAP") -> #NAME?
A8: J36.SI | B8: J36 SP Equity | C8: YES | D8: =BDP(B8,"NAME") -> #NAME? | E8: =BDP(B8,"PX_LAST") -> #NAME? | F8: =BDP(B8,"GICS_SECTOR_NAME") -> #NAME? | G8: =BDP(B8,"CUR_MKT_CAP") -> #NAME?
A9: C6L.SI | B9: C6L SP Equity | C9: YES | D9: =BDP(B9,"NAME") -> #NAME? | E9: =BDP(B9,"PX_LAST") -> #NAME? | F9: =BDP(B9,"GICS_SECTOR_NAME") -> #NAME? | G9: =BDP(B9,"CUR_MKT_CAP") -> #NAME?
A10: F34.SI | B10: F34 SP Equity | C10: YES | D10: =BDP(B10,"NAME") -> #NAME? | E10: =BDP(B10,"PX_LAST") -> #NAME? | F10: =BDP(B10,"GICS_SECTOR_NAME") -> #NAME? | G10: =BDP(B10,"CUR_MKT_CAP") -> #NAME?
A11: H78.SI | B11: H78 SP Equity | C11: YES | D11: =BDP(B11,"NAME") -> #NAME? | E11: =BDP(B11,"PX_LAST") -> #NAME? | F11: =BDP(B11,"GICS_SECTOR_NAME") -> #NAME? | G11: =BDP(B11,"CUR_MKT_CAP") -> #NAME?
A12: BN4.SI | B12: BN4 SP Equity | C12: YES | D12: =BDP(B12,"NAME") -> #NAME? | E12: =BDP(B12,"PX_LAST") -> #NAME? | F12: =BDP(B12,"GICS_SECTOR_NAME") -> #NAME? | G12: =BDP(B12,"CUR_MKT_CAP") -> #NAME?
A13: C38U.SI | B13: C38U SP Equity | C13: YES | D13: =BDP(B13,"NAME") -> #NAME? | E13: =BDP(B13,"PX_LAST") -> #NAME? | F13: =BDP(B13,"GICS_SECTOR_NAME") -> #NAME? | G13: =BDP(B13,"CUR_MKT_CAP") -> #NAME?
... A81: ES3.SI | B81: ES3 SP Equity | C81: BENCH | D81: =BDP(B81,"NAME") -> #NAME? | E81: =BDP(B81,"PX_LAST") -> #NAME? | F81: =BDP(B81,"GICS_SECTOR_NAME") -> #NAME? | G81: =BDP(B81,"CUR_MKT_CAP") -> #NAME?

Sheet Prices
A1: Date | B1: D05.SI | C1: O39.SI | D1: Z74.SI | E1: U11.SI | F1: S63.SI | G1: S68.SI | H1: J36.SI | I1: C6L.SI | J1: F34.SI | K1: H78.SI | L1: BN4.SI | M1: C38U.SI | N1: U14.SI | O1: 5E2.SI | P1: G13.SI | Q1: S58.SI | R1: N2IU.SI | S1: C09.SI | T1: D01.SI | U1: M44U.SI | V1: EB5.SI | W1: ME8U.SI | X1: AJBU.SI | Y1: VC2.SI | Z1: U06.SI | AA1: OV8.SI | AB1: V03.SI | AC1: J69U.SI | AD1: T82U.SI | AE1: K71U.SI | AF1: U10.SI | AG1: TQ5.SI | AH1: CJL.SI | AI1: BUOU.SI | AJ1: S59.SI | AK1: E5H.SI | AL1: H02.SI | AM1: HMN.SI | AN1: A7RU.SI | AO1: P8Z.SI | AP1: C52.SI | AQ1: AWX.SI | AR1: AIY.SI | AS1: C2PU.SI | AT1: F17.SI | AU1: H15.SI | AV1: H22.SI | AW1: 558.SI | AX1: NS8U.SI | AY1: 8Y.SI | AZ1: F99.SI | BA1: TS0U.SI | BB1: 9A4U.SI | BC1: 8C8U.SI | BD1: SEB.SI | BE1: Z25.SI | BF1: AP4.SI | BG1: P40U.SI | BH1: B61.SI | BI1: NTDU.SI | BJ1: W05.SI | BK1: Q5T.SI | BL1: BEC.SI | BM1: E28.SI | BN1: UIBU.SI | BO1: AU8U.SI | BP1: P52.SI | BQ1: S41.SI | BR1: S61.SI | BS1: PCT.SI | BT1: ADN.SI | BU1: F9D.SI | BV1: FHH.SI | BW1: J85.SI | BX1: T6I.SI | BY1: RE4.SI | BZ1: 544.SI | CA1: CRPU.SI | CB1: DCRU.SI
A2: =BDH(Universe!B2,"PX_LAST",Control!$B$2,Control!$B$3,"Dir=V","Dts=S","Sort=A","CshAdjNormal=Y","CshAdjAbnormal=Y","CapChg=Y","Fill=P","Days=A") -> #NAME? | C2: =BDH(Universe!B3,"PX_LAST",Control!$B$2,Control!$B$3,"Dir=V","Dts=H","Sort=A","CshAdjNormal=Y","CshAdjAbnormal=Y","CapChg=Y","Fill=P","Days=A") -> #NAME? | D2: =BDH(Universe!B4,"PX_LAST",Control!$B$2,Control!$B$3,"Dir=V","Dts=H","Sort=A","CshAdjNormal=Y","CshAdjAbnormal=Y","CapChg=Y","Fill=P","Days=A") -> #NAME? | E2: =BDH(Universe!B5,"PX_LAST",Control!$B$2,Control!$B$3,"Dir=V","Dts=H","Sort=A","CshAdjNormal=Y","CshAdjAbnormal=Y","CapChg=Y","Fill=P","Days=A") -> #NAME? | F2: =BDH(Universe!B6,"PX_LAST",Control!$B$2,Control!$B$3,"Dir=V","Dts=H","Sort=A","CshAdjNormal=Y","CshAdjAbnormal=Y","CapChg=Y","Fill=P","Days=A") -> #NAME? | G2: =BDH(Universe!B7,"PX_LAST",Control!$B$2,Control!$B$3,"Dir=V","Dts=H","Sort=A","CshAdjNormal=Y","CshAdjAbnormal=Y","CapChg=Y","Fill=P","Days=A") -> #NAME? | H2: =BDH(Universe!B8,"PX_LAST",Control!$B$2,Control!$B$3,"Dir=V","Dts=H","Sort=A","CshAdjNormal=Y","CshAdjAbnormal=Y","CapChg=Y","Fill=P","Days=A") -> #NAME? | I2: =BDH(Universe!B9,"PX_LAST",Control!$B$2,Control!$B$3,"Dir=V","Dts=H","Sort=A","CshAdjNormal=Y","CshAdjAbnormal=Y","CapChg=Y","Fill=P","Days=A") -> #NAME? | J2: =BDH(Universe!B10,"PX_LAST",Control!$B$2,Control!$B$3,"Dir=V","Dts=H","Sort=A","CshAdjNormal=Y","CshAdjAbnormal=Y","CapChg=Y","Fill=P","Days=A") -> #NAME? | K2: =BDH(Universe!B11,"PX_LAST",Control!$B$2,Control!$B$3,"Dir=V","Dts=H","Sort=A","CshAdjNormal=Y","CshAdjAbnormal=Y","CapChg=Y","Fill=P","Days=A") -> #NAME? | L2: =BDH(Universe!B12,"PX_LAST",Control!$B$2,Control!$B$3,"Dir=V","Dts=H","Sort=A","CshAdjNormal=Y","CshAdjAbnormal=Y","CapChg=Y","Fill=P","Days=A") -> #NAME? | M2: =BDH(Universe!B13,"PX_LAST",Control!$B$2,Control!$B$3,"Dir=V","Dts=H","Sort=A","CshAdjNormal=Y","CshAdjAbnormal=Y","CapChg=Y","Fill=P","Days=A") -> #NAME? | N2: =BDH(Universe!B14,"PX_LAST",Control!$B$2,Control!$B$3,"Dir=V","Dts=H","Sort=A","CshAdjNormal=Y","CshAdjAbnormal=Y","CapChg=Y","Fill=P","Days=A") -> #NAME? | O2: =BDH(Universe!B15,"PX_LAST",Control!$B$2,Control!$B$3,"Dir=V","Dts=H","Sort=A","CshAdjNormal=Y","CshAdjAbnormal=Y","CapChg=Y","Fill=P","Days=A") -> #NAME? | P2: =BDH(Universe!B16,"PX_LAST",Control!$B$2,Control!$B$3,"Dir=V","Dts=H","Sort=A","CshAdjNormal=Y","CshAdjAbnormal=Y","CapChg=Y","Fill=P","Days=A") -> #NAME? | Q2: =BDH(Universe!B17,"PX_LAST",Control!$B$2,Control!$B$3,"Dir=V","Dts=H","Sort=A","CshAdjNormal=Y","CshAdjAbnormal=Y","CapChg=Y","Fill=P","Days=A") -> #NAME? | R2: =BDH(Universe!B18,"PX_LAST",Control!$B$2,Control!$B$3,"Dir=V","Dts=H","Sort=A","CshAdjNormal=Y","CshAdjAbnormal=Y","CapChg=Y","Fill=P","Days=A") -> #NAME? | S2: =BDH(Universe!B19,"PX_LAST",Control!$B$2,Control!$B$3,"Dir=V","Dts=H","Sort=A","CshAdjNormal=Y","CshAdjAbnormal=Y","CapChg=Y","Fill=P","Days=A") -> #NAME? | T2: =BDH(Universe!B20,"PX_LAST",Control!$B$2,Control!$B$3,"Dir=V","Dts=H","Sort=A","CshAdjNormal=Y","CshAdjAbnormal=Y","CapChg=Y","Fill=P","Days=A") -> #NAME? | U2: =BDH(Universe!B21,"PX_LAST",Control!$B$2,Control!$B$3,"Dir=V","Dts=H","Sort=A","CshAdjNormal=Y","CshAdjAbnormal=Y","CapChg=Y","Fill=P","Days=A") -> #NAME? | V2: =BDH(Universe!B22,"PX_LAST",Control!$B$2,Control!$B$3,"Dir=V","Dts=H","Sort=A","CshAdjNormal=Y","CshAdjAbnormal=Y","CapChg=Y","Fill=P","Days=A") -> #NAME? | W2: =BDH(Universe!B23,"PX_LAST",Control!$B$2,Control!$B$3,"Dir=V","Dts=H","Sort=A","CshAdjNormal=Y","CshAdjAbnormal=Y","CapChg=Y","Fill=P","Days=A") -> #NAME? | X2: =BDH(Universe!B24,"PX_LAST",Control!$B$2,Control!$B$3,"Dir=V","Dts=H","Sort=A","CshAdjNormal=Y","CshAdjAbnormal=Y","CapChg=Y","Fill=P","Days=A") -> #NAME? | Y2: =BDH(Universe!B25,"PX_LAST",Control!$B$2,Control!$B$3,"Dir=V","Dts=H","Sort=A","CshAdjNormal=Y","CshAdjAbnormal=Y","CapChg=Y","Fill=P","Days=A") -> #NAME? | Z2: =BDH(Universe!B26,"PX_LAST",Control!$B$2,Control!$B$3,"Dir=V","Dts=H","Sort=A","CshAdjNormal=Y","CshAdjAbnormal=Y","CapChg=Y","Fill=P","Days=A") -> #NAME? | AA2: =BDH(Universe!B27,"PX_LAST",Control!$B$2,Control!$B$3,"Dir=V","Dts=H","Sort=A","CshAdjNormal=Y","CshAdjAbnormal=Y","CapChg=Y","Fill=P","Days=A") -> #NAME? | AB2: =BDH(Universe!B28,"PX_LAST",Control!$B$2,Control!$B$3,"Dir=V","Dts=H","Sort=A","CshAdjNormal=Y","CshAdjAbnormal=Y","CapChg=Y","Fill=P","Days=A") -> #NAME? | AC2: =BDH(Universe!B29,"PX_LAST",Control!$B$2,Control!$B$3,"Dir=V","Dts=H","Sort=A","CshAdjNormal=Y","CshAdjAbnormal=Y","CapChg=Y","Fill=P","Days=A") -> #NAME? | AD2: =BDH(Universe!B30,"PX_LAST",Control!$B$2,Control!$B$3,"Dir=V","Dts=H","Sort=A","CshAdjNormal=Y","CshAdjAbnormal=Y","CapChg=Y","Fill=P","Days=A") -> #NAME? | AE2: =BDH(Universe!B31,"PX_LAST",Control!$B$2,Control!$B$3,"Dir=V","Dts=H","Sort=A","CshAdjNormal=Y","CshAdjAbnormal=Y","CapChg=Y","Fill=P","Days=A") -> #NAME? | AF2: =BDH(Universe!B32,"PX_LAST",Control!$B$2,Control!$B$3,"Dir=V","Dts=H","Sort=A","CshAdjNormal=Y","CshAdjAbnormal=Y","CapChg=Y","Fill=P","Days=A") -> #NAME? | AG2: =BDH(Universe!B33,"PX_LAST",Control!$B$2,Control!$B$3,"Dir=V","Dts=H","Sort=A","CshAdjNormal=Y","CshAdjAbnormal=Y","CapChg=Y","Fill=P","Days=A") -> #NAME? | AH2: =BDH(Universe!B34,"PX_LAST",Control!$B$2,Control!$B$3,"Dir=V","Dts=H","Sort=A","CshAdjNormal=Y","CshAdjAbnormal=Y","CapChg=Y","Fill=P","Days=A") -> #NAME? | AI2: =BDH(Universe!B35,"PX_LAST",Control!$B$2,Control!$B$3,"Dir=V","Dts=H","Sort=A","CshAdjNormal=Y","CshAdjAbnormal=Y","CapChg=Y","Fill=P","Days=A") -> #NAME? | AJ2: =BDH(Universe!B36,"PX_LAST",Control!$B$2,Control!$B$3,"Dir=V","Dts=H","Sort=A","CshAdjNormal=Y","CshAdjAbnormal=Y","CapChg=Y","Fill=P","Days=A") -> #NAME? | AK2: =BDH(Universe!B37,"PX_LAST",Control!$B$2,Control!$B$3,"Dir=V","Dts=H","Sort=A","CshAdjNormal=Y","CshAdjAbnormal=Y","CapChg=Y","Fill=P","Days=A") -> #NAME? | AL2: =BDH(Universe!B38,"PX_LAST",Control!$B$2,Control!$B$3,"Dir=V","Dts=H","Sort=A","CshAdjNormal=Y","CshAdjAbnormal=Y","CapChg=Y","Fill=P","Days=A") -> #NAME? | AM2: =BDH(Universe!B39,"PX_LAST",Control!$B$2,Control!$B$3,"Dir=V","Dts=H","Sort=A","CshAdjNormal=Y","CshAdjAbnormal=Y","CapChg=Y","Fill=P","Days=A") -> #NAME? | AN2: =BDH(Universe!B40,"PX_LAST",Control!$B$2,Control!$B$3,"Dir=V","Dts=H","Sort=A","CshAdjNormal=Y","CshAdjAbnormal=Y","CapChg=Y","Fill=P","Days=A") -> #NAME? | AO2: =BDH(Universe!B41,"PX_LAST",Control!$B$2,Control!$B$3,"Dir=V","Dts=H","Sort=A","CshAdjNormal=Y","CshAdjAbnormal=Y","CapChg=Y","Fill=P","Days=A") -> #NAME? | AP2: =BDH(Universe!B42,"PX_LAST",Control!$B$2,Control!$B$3,"Dir=V","Dts=H","Sort=A","CshAdjNormal=Y","CshAdjAbnormal=Y","CapChg=Y","Fill=P","Days=A") -> #NAME? | AQ2: =BDH(Universe!B43,"PX_LAST",Control!$B$2,Control!$B$3,"Dir=V","Dts=H","Sort=A","CshAdjNormal=Y","CshAdjAbnormal=Y","CapChg=Y","Fill=P","Days=A") -> #NAME? | AR2: =BDH(Universe!B44,"PX_LAST",Control!$B$2,Control!$B$3,"Dir=V","Dts=H","Sort=A","CshAdjNormal=Y","CshAdjAbnormal=Y","CapChg=Y","Fill=P","Days=A") -> #NAME? | AS2: =BDH(Universe!B45,"PX_LAST",Control!$B$2,Control!$B$3,"Dir=V","Dts=H","Sort=A","CshAdjNormal=Y","CshAdjAbnormal=Y","CapChg=Y","Fill=P","Days=A") -> #NAME? | AT2: =BDH(Universe!B46,"PX_LAST",Control!$B$2,Control!$B$3,"Dir=V","Dts=H","Sort=A","CshAdjNormal=Y","CshAdjAbnormal=Y","CapChg=Y","Fill=P","Days=A") -> #NAME? | AU2: =BDH(Universe!B47,"PX_LAST",Control!$B$2,Control!$B$3,"Dir=V","Dts=H","Sort=A","CshAdjNormal=Y","CshAdjAbnormal=Y","CapChg=Y","Fill=P","Days=A") -> #NAME? | AV2: =BDH(Universe!B48,"PX_LAST",Control!$B$2,Control!$B$3,"Dir=V","Dts=H","Sort=A","CshAdjNormal=Y","CshAdjAbnormal=Y","CapChg=Y","Fill=P","Days=A") -> #NAME? | AW2: =BDH(Universe!B49,"PX_LAST",Control!$B$2,Control!$B$3,"Dir=V","Dts=H","Sort=A","CshAdjNormal=Y","CshAdjAbnormal=Y","CapChg=Y","Fill=P","Days=A") -> #NAME? | AX2: =BDH(Universe!B50,"PX_LAST",Control!$B$2,Control!$B$3,"Dir=V","Dts=H","Sort=A","CshAdjNormal=Y","CshAdjAbnormal=Y","CapChg=Y","Fill=P","Days=A") -> #NAME? | AY2: =BDH(Universe!B51,"PX_LAST",Control!$B$2,Control!$B$3,"Dir=V","Dts=H","Sort=A","CshAdjNormal=Y","CshAdjAbnormal=Y","CapChg=Y","Fill=P","Days=A") -> #NAME? | AZ2: =BDH(Universe!B52,"PX_LAST",Control!$B$2,Control!$B$3,"Dir=V","Dts=H","Sort=A","CshAdjNormal=Y","CshAdjAbnormal=Y","CapChg=Y","Fill=P","Days=A") -> #NAME? | BA2: =BDH(Universe!B53,"PX_LAST",Control!$B$2,Control!$B$3,"Dir=V","Dts=H","Sort=A","CshAdjNormal=Y","CshAdjAbnormal=Y","CapChg=Y","Fill=P","Days=A") -> #NAME? | BB2: =BDH(Universe!B54,"PX_LAST",Control!$B$2,Control!$B$3,"Dir=V","Dts=H","Sort=A","CshAdjNormal=Y","CshAdjAbnormal=Y","CapChg=Y","Fill=P","Days=A") -> #NAME? | BC2: =BDH(Universe!B55,"PX_LAST",Control!$B$2,Control!$B$3,"Dir=V","Dts=H","Sort=A","CshAdjNormal=Y","CshAdjAbnormal=Y","CapChg=Y","Fill=P","Days=A") -> #NAME? | BD2: =BDH(Universe!B56,"PX_LAST",Control!$B$2,Control!$B$3,"Dir=V","Dts=H","Sort=A","CshAdjNormal=Y","CshAdjAbnormal=Y","CapChg=Y","Fill=P","Days=A") -> #NAME? | BE2: =BDH(Universe!B57,"PX_LAST",Control!$B$2,Control!$B$3,"Dir=V","Dts=H","Sort=A","CshAdjNormal=Y","CshAdjAbnormal=Y","CapChg=Y","Fill=P","Days=A") -> #NAME? | BF2: =BDH(Universe!B58,"PX_LAST",Control!$B$2,Control!$B$3,"Dir=V","Dts=H","Sort=A","CshAdjNormal=Y","CshAdjAbnormal=Y","CapChg=Y","Fill=P","Days=A") -> #NAME? | BG2: =BDH(Universe!B59,"PX_LAST",Control!$B$2,Control!$B$3,"Dir=V","Dts=H","Sort=A","CshAdjNormal=Y","CshAdjAbnormal=Y","CapChg=Y","Fill=P","Days=A") -> #NAME? | BH2: =BDH(Universe!B60,"PX_LAST",Control!$B$2,Control!$B$3,"Dir=V","Dts=H","Sort=A","CshAdjNormal=Y","CshAdjAbnormal=Y","CapChg=Y","Fill=P","Days=A") -> #NAME? | BI2: =BDH(Universe!B61,"PX_LAST",Control!$B$2,Control!$B$3,"Dir=V","Dts=H","Sort=A","CshAdjNormal=Y","CshAdjAbnormal=Y","CapChg=Y","Fill=P","Days=A") -> #NAME? | BJ2: =BDH(Universe!B62,"PX_LAST",Control!$B$2,Control!$B$3,"Dir=V","Dts=H","Sort=A","CshAdjNormal=Y","CshAdjAbnormal=Y","CapChg=Y","Fill=P","Days=A") -> #NAME? | BK2: =BDH(Universe!B63,"PX_LAST",Control!$B$2,Control!$B$3,"Dir=V","Dts=H","Sort=A","CshAdjNormal=Y","CshAdjAbnormal=Y","CapChg=Y","Fill=P","Days=A") -> #NAME? | BL2: =BDH(Universe!B64,"PX_LAST",Control!$B$2,Control!$B$3,"Dir=V","Dts=H","Sort=A","CshAdjNormal=Y","CshAdjAbnormal=Y","CapChg=Y","Fill=P","Days=A") -> #NAME? | BM2: =BDH(Universe!B65,"PX_LAST",Control!$B$2,Control!$B$3,"Dir=V","Dts=H","Sort=A","CshAdjNormal=Y","CshAdjAbnormal=Y","CapChg=Y","Fill=P","Days=A") -> #NAME? | BN2: =BDH(Universe!B66,"PX_LAST",Control!$B$2,Control!$B$3,"Dir=V","Dts=H","Sort=A","CshAdjNormal=Y","CshAdjAbnormal=Y","CapChg=Y","Fill=P","Days=A") -> #NAME? | BO2: =BDH(Universe!B67,"PX_LAST",Control!$B$2,Control!$B$3,"Dir=V","Dts=H","Sort=A","CshAdjNormal=Y","CshAdjAbnormal=Y","CapChg=Y","Fill=P","Days=A") -> #NAME? | BP2: =BDH(Universe!B68,"PX_LAST",Control!$B$2,Control!$B$3,"Dir=V","Dts=H","Sort=A","CshAdjNormal=Y","CshAdjAbnormal=Y","CapChg=Y","Fill=P","Days=A") -> #NAME? | BQ2: =BDH(Universe!B69,"PX_LAST",Control!$B$2,Control!$B$3,"Dir=V","Dts=H","Sort=A","CshAdjNormal=Y","CshAdjAbnormal=Y","CapChg=Y","Fill=P","Days=A") -> #NAME? | BR2: =BDH(Universe!B70,"PX_LAST",Control!$B$2,Control!$B$3,"Dir=V","Dts=H","Sort=A","CshAdjNormal=Y","CshAdjAbnormal=Y","CapChg=Y","Fill=P","Days=A") -> #NAME? | BS2: =BDH(Universe!B71,"PX_LAST",Control!$B$2,Control!$B$3,"Dir=V","Dts=H","Sort=A","CshAdjNormal=Y","CshAdjAbnormal=Y","CapChg=Y","Fill=P","Days=A") -> #NAME? | BT2: =BDH(Universe!B72,"PX_LAST",Control!$B$2,Control!$B$3,"Dir=V","Dts=H","Sort=A","CshAdjNormal=Y","CshAdjAbnormal=Y","CapChg=Y","Fill=P","Days=A") -> #NAME? | BU2: =BDH(Universe!B73,"PX_LAST",Control!$B$2,Control!$B$3,"Dir=V","Dts=H","Sort=A","CshAdjNormal=Y","CshAdjAbnormal=Y","CapChg=Y","Fill=P","Days=A") -> #NAME? | BV2: =BDH(Universe!B74,"PX_LAST",Control!$B$2,Control!$B$3,"Dir=V","Dts=H","Sort=A","CshAdjNormal=Y","CshAdjAbnormal=Y","CapChg=Y","Fill=P","Days=A") -> #NAME? | BW2: =BDH(Universe!B75,"PX_LAST",Control!$B$2,Control!$B$3,"Dir=V","Dts=H","Sort=A","CshAdjNormal=Y","CshAdjAbnormal=Y","CapChg=Y","Fill=P","Days=A") -> #NAME? | BX2: =BDH(Universe!B76,"PX_LAST",Control!$B$2,Control!$B$3,"Dir=V","Dts=H","Sort=A","CshAdjNormal=Y","CshAdjAbnormal=Y","CapChg=Y","Fill=P","Days=A") -> #NAME? | BY2: =BDH(Universe!B77,"PX_LAST",Control!$B$2,Control!$B$3,"Dir=V","Dts=H","Sort=A","CshAdjNormal=Y","CshAdjAbnormal=Y","CapChg=Y","Fill=P","Days=A") -> #NAME? | BZ2: =BDH(Universe!B78,"PX_LAST",Control!$B$2,Control!$B$3,"Dir=V","Dts=H","Sort=A","CshAdjNormal=Y","CshAdjAbnormal=Y","CapChg=Y","Fill=P","Days=A") -> #NAME? | CA2: =BDH(Universe!B79,"PX_LAST",Control!$B$2,Control!$B$3,"Dir=V","Dts=H","Sort=A","CshAdjNormal=Y","CshAdjAbnormal=Y","CapChg=Y","Fill=P","Days=A") -> #NAME? | CB2: =BDH(Universe!B80,"PX_LAST",Control!$B$2,Control!$B$3,"Dir=V","Dts=H","Sort=A","CshAdjNormal=Y","CshAdjAbnormal=Y","CapChg=Y","Fill=P","Days=A") -> #NAME?

Sheet Prices_Notes
A1: Prices sheet notes
A2: After Bloomberg refresh:
A3: • Cell A2 spills TWO columns: Date (col A) + first ticker values (col B).
A4: • Columns C onward spill VALUES only (Dts=H) aligned to the same date rows.
A5: • If a column shows #N/A or partial history, check the Bloomberg code on Universe.
A6: • Do NOT change row-1 headers — they must stay Yahoo .SI names for the converter.
A7: • When export is ready: copy Prices → Paste Special Values into a new book, Save As CSV UTF-8,
A8: or run: python bloomberg/bbg_to_csv.py --xlsx SG_Bloomberg_Historical_Pull.xlsx
A9: • Fill=P carries prices over non-trading days; Days=A = all calendar days.
A10: If you prefer exchange trading days only, remove Days=A from the BDH formulas.

Sheet Book
A1: Date | B1: D05.SI | C1: O39.SI | D1: Z74.SI | E1: U11.SI | F1: S63.SI | G1: S68.SI | H1: J36.SI | I1: C6L.SI | J1: F34.SI | K1: H78.SI | L1: BN4.SI | M1: C38U.SI | N1: U14.SI | O1: 5E2.SI | P1: G13.SI | Q1: S58.SI | R1: N2IU.SI | S1: C09.SI | T1: D01.SI | U1: M44U.SI | V1: EB5.SI | W1: ME8U.SI | X1: AJBU.SI | Y1: VC2.SI | Z1: U06.SI | AA1: OV8.SI | AB1: V03.SI | AC1: J69U.SI | AD1: T82U.SI | AE1: K71U.SI | AF1: U10.SI | AG1: TQ5.SI | AH1: CJL.SI | AI1: BUOU.SI | AJ1: S59.SI | AK1: E5H.SI | AL1: H02.SI | AM1: HMN.SI | AN1: A7RU.SI | AO1: P8Z.SI | AP1: C52.SI | AQ1: AWX.SI | AR1: AIY.SI | AS1: C2PU.SI | AT1: F17.SI | AU1: H15.SI | AV1: H22.SI | AW1: 558.SI | AX1: NS8U.SI | AY1: 8Y.SI | AZ1: F99.SI | BA1: TS0U.SI | BB1: 9A4U.SI | BC1: 8C8U.SI | BD1: SEB.SI | BE1: Z25.SI | BF1: AP4.SI | BG1: P40U.SI | BH1: B61.SI | BI1: NTDU.SI | BJ1: W05.SI | BK1: Q5T.SI | BL1: BEC.SI | BM1: E28.SI | BN1: UIBU.SI | BO1: AU8U.SI | BP1: P52.SI | BQ1: S41.SI | BR1: S61.SI | BS1: PCT.SI | BT1: ADN.SI | BU1: F9D.SI | BV1: FHH.SI | BW1: J85.SI | BX1: T6I.SI | BY1: RE4.SI | BZ1: 544.SI | CA1: CRPU.SI | CB1: DCRU.SI
A2: =BDH(Universe!B2,Control!$B$5,Control!$B$2,Control!$B$3,"Dir=V","Dts=S","Sort=A","Per="&Control!$B$6,"Fill=P") -> #NAME? | C2: =BDH(Universe!B3,Control!$B$5,Control!$B$2,Control!$B$3,"Dir=V","Dts=H","Sort=A","Per="&Control!$B$6,"Fill=P") -> #NAME? | D2: =BDH(Universe!B4,Control!$B$5,Control!$B$2,Control!$B$3,"Dir=V","Dts=H","Sort=A","Per="&Control!$B$6,"Fill=P") -> #NAME? | E2: =BDH(Universe!B5,Control!$B$5,Control!$B$2,Control!$B$3,"Dir=V","Dts=H","Sort=A","Per="&Control!$B$6,"Fill=P") -> #NAME? | F2: =BDH(Universe!B6,Control!$B$5,Control!$B$2,Control!$B$3,"Dir=V","Dts=H","Sort=A","Per="&Control!$B$6,"Fill=P") -> #NAME? | G2: =BDH(Universe!B7,Control!$B$5,Control!$B$2,Control!$B$3,"Dir=V","Dts=H","Sort=A","Per="&Control!$B$6,"Fill=P") -> #NAME? | H2: =BDH(Universe!B8,Control!$B$5,Control!$B$2,Control!$B$3,"Dir=V","Dts=H","Sort=A","Per="&Control!$B$6,"Fill=P") -> #NAME? | I2: =BDH(Universe!B9,Control!$B$5,Control!$B$2,Control!$B$3,"Dir=V","Dts=H","Sort=A","Per="&Control!$B$6,"Fill=P") -> #NAME? | J2: =BDH(Universe!B10,Control!$B$5,Control!$B$2,Control!$B$3,"Dir=V","Dts=H","Sort=A","Per="&Control!$B$6,"Fill=P") -> #NAME? | K2: =BDH(Universe!B11,Control!$B$5,Control!$B$2,Control!$B$3,"Dir=V","Dts=H","Sort=A","Per="&Control!$B$6,"Fill=P") -> #NAME? | L2: =BDH(Universe!B12,Control!$B$5,Control!$B$2,Control!$B$3,"Dir=V","Dts=H","Sort=A","Per="&Control!$B$6,"Fill=P") -> #NAME? | M2: =BDH(Universe!B13,Control!$B$5,Control!$B$2,Control!$B$3,"Dir=V","Dts=H","Sort=A","Per="&Control!$B$6,"Fill=P") -> #NAME? | N2: =BDH(Universe!B14,Control!$B$5,Control!$B$2,Control!$B$3,"Dir=V","Dts=H","Sort=A","Per="&Control!$B$6,"Fill=P") -> #NAME? | O2: =BDH(Universe!B15,Control!$B$5,Control!$B$2,Control!$B$3,"Dir=V","Dts=H","Sort=A","Per="&Control!$B$6,"Fill=P") -> #NAME? | P2: =BDH(Universe!B16,Control!$B$5,Control!$B$2,Control!$B$3,"Dir=V","Dts=H","Sort=A","Per="&Control!$B$6,"Fill=P") -> #NAME? | Q2: =BDH(Universe!B17,Control!$B$5,Control!$B$2,Control!$B$3,"Dir=V","Dts=H","Sort=A","Per="&Control!$B$6,"Fill=P") -> #NAME? | R2: =BDH(Universe!B18,Control!$B$5,Control!$B$2,Control!$B$3,"Dir=V","Dts=H","Sort=A","Per="&Control!$B$6,"Fill=P") -> #NAME? | S2: =BDH(Universe!B19,Control!$B$5,Control!$B$2,Control!$B$3,"Dir=V","Dts=H","Sort=A","Per="&Control!$B$6,"Fill=P") -> #NAME? | T2: =BDH(Universe!B20,Control!$B$5,Control!$B$2,Control!$B$3,"Dir=V","Dts=H","Sort=A","Per="&Control!$B$6,"Fill=P") -> #NAME? | U2: =BDH(Universe!B21,Control!$B$5,Control!$B$2,Control!$B$3,"Dir=V","Dts=H","Sort=A","Per="&Control!$B$6,"Fill=P") -> #NAME? | V2: =BDH(Universe!B22,Control!$B$5,Control!$B$2,Control!$B$3,"Dir=V","Dts=H","Sort=A","Per="&Control!$B$6,"Fill=P") -> #NAME? | W2: =BDH(Universe!B23,Control!$B$5,Control!$B$2,Control!$B$3,"Dir=V","Dts=H","Sort=A","Per="&Control!$B$6,"Fill=P") -> #NAME? | X2: =BDH(Universe!B24,Control!$B$5,Control!$B$2,Control!$B$3,"Dir=V","Dts=H","Sort=A","Per="&Control!$B$6,"Fill=P") -> #NAME? | Y2: =BDH(Universe!B25,Control!$B$5,Control!$B$2,Control!$B$3,"Dir=V","Dts=H","Sort=A","Per="&Control!$B$6,"Fill=P") -> #NAME? | Z2: =BDH(Universe!B26,Control!$B$5,Control!$B$2,Control!$B$3,"Dir=V","Dts=H","Sort=A","Per="&Control!$B$6,"Fill=P") -> #NAME? | AA2: =BDH(Universe!B27,Control!$B$5,Control!$B$2,Control!$B$3,"Dir=V","Dts=H","Sort=A","Per="&Control!$B$6,"Fill=P") -> #NAME? | AB2: =BDH(Universe!B28,Control!$B$5,Control!$B$2,Control!$B$3,"Dir=V","Dts=H","Sort=A","Per="&Control!$B$6,"Fill=P") -> #NAME? | AC2: =BDH(Universe!B29,Control!$B$5,Control!$B$2,Control!$B$3,"Dir=V","Dts=H","Sort=A","Per="&Control!$B$6,"Fill=P") -> #NAME? | AD2: =BDH(Universe!B30,Control!$B$5,Control!$B$2,Control!$B$3,"Dir=V","Dts=H","Sort=A","Per="&Control!$B$6,"Fill=P") -> #NAME? | AE2: =BDH(Universe!B31,Control!$B$5,Control!$B$2,Control!$B$3,"Dir=V","Dts=H","Sort=A","Per="&Control!$B$6,"Fill=P") -> #NAME? | AF2: =BDH(Universe!B32,Control!$B$5,Control!$B$2,Control!$B$3,"Dir=V","Dts=H","Sort=A","Per="&Control!$B$6,"Fill=P") -> #NAME? | AG2: =BDH(Universe!B33,Control!$B$5,Control!$B$2,Control!$B$3,"Dir=V","Dts=H","Sort=A","Per="&Control!$B$6,"Fill=P") -> #NAME? | AH2: =BDH(Universe!B34,Control!$B$5,Control!$B$2,Control!$B$3,"Dir=V","Dts=H","Sort=A","Per="&Control!$B$6,"Fill=P") -> #NAME? | AI2: =BDH(Universe!B35,Control!$B$5,Control!$B$2,Control!$B$3,"Dir=V","Dts=H","Sort=A","Per="&Control!$B$6,"Fill=P") -> #NAME? | AJ2: =BDH(Universe!B36,Control!$B$5,Control!$B$2,Control!$B$3,"Dir=V","Dts=H","Sort=A","Per="&Control!$B$6,"Fill=P") -> #NAME? | AK2: =BDH(Universe!B37,Control!$B$5,Control!$B$2,Control!$B$3,"Dir=V","Dts=H","Sort=A","Per="&Control!$B$6,"Fill=P") -> #NAME? | AL2: =BDH(Universe!B38,Control!$B$5,Control!$B$2,Control!$B$3,"Dir=V","Dts=H","Sort=A","Per="&Control!$B$6,"Fill=P") -> #NAME? | AM2: =BDH(Universe!B39,Control!$B$5,Control!$B$2,Control!$B$3,"Dir=V","Dts=H","Sort=A","Per="&Control!$B$6,"Fill=P") -> #NAME? | AN2: =BDH(Universe!B40,Control!$B$5,Control!$B$2,Control!$B$3,"Dir=V","Dts=H","Sort=A","Per="&Control!$B$6,"Fill=P") -> #NAME? | AO2: =BDH(Universe!B41,Control!$B$5,Control!$B$2,Control!$B$3,"Dir=V","Dts=H","Sort=A","Per="&Control!$B$6,"Fill=P") -> #NAME? | AP2: =BDH(Universe!B42,Control!$B$5,Control!$B$2,Control!$B$3,"Dir=V","Dts=H","Sort=A","Per="&Control!$B$6,"Fill=P") -> #NAME? | AQ2: =BDH(Universe!B43,Control!$B$5,Control!$B$2,Control!$B$3,"Dir=V","Dts=H","Sort=A","Per="&Control!$B$6,"Fill=P") -> #NAME? | AR2: =BDH(Universe!B44,Control!$B$5,Control!$B$2,Control!$B$3,"Dir=V","Dts=H","Sort=A","Per="&Control!$B$6,"Fill=P") -> #NAME? | AS2: =BDH(Universe!B45,Control!$B$5,Control!$B$2,Control!$B$3,"Dir=V","Dts=H","Sort=A","Per="&Control!$B$6,"Fill=P") -> #NAME? | AT2: =BDH(Universe!B46,Control!$B$5,Control!$B$2,Control!$B$3,"Dir=V","Dts=H","Sort=A","Per="&Control!$B$6,"Fill=P") -> #NAME? | AU2: =BDH(Universe!B47,Control!$B$5,Control!$B$2,Control!$B$3,"Dir=V","Dts=H","Sort=A","Per="&Control!$B$6,"Fill=P") -> #NAME? | AV2: =BDH(Universe!B48,Control!$B$5,Control!$B$2,Control!$B$3,"Dir=V","Dts=H","Sort=A","Per="&Control!$B$6,"Fill=P") -> #NAME? | AW2: =BDH(Universe!B49,Control!$B$5,Control!$B$2,Control!$B$3,"Dir=V","Dts=H","Sort=A","Per="&Control!$B$6,"Fill=P") -> #NAME? | AX2: =BDH(Universe!B50,Control!$B$5,Control!$B$2,Control!$B$3,"Dir=V","Dts=H","Sort=A","Per="&Control!$B$6,"Fill=P") -> #NAME? | AY2: =BDH(Universe!B51,Control!$B$5,Control!$B$2,Control!$B$3,"Dir=V","Dts=H","Sort=A","Per="&Control!$B$6,"Fill=P") -> #NAME? | AZ2: =BDH(Universe!B52,Control!$B$5,Control!$B$2,Control!$B$3,"Dir=V","Dts=H","Sort=A","Per="&Control!$B$6,"Fill=P") -> #NAME? | BA2: =BDH(Universe!B53,Control!$B$5,Control!$B$2,Control!$B$3,"Dir=V","Dts=H","Sort=A","Per="&Control!$B$6,"Fill=P") -> #NAME? | BB2: =BDH(Universe!B54,Control!$B$5,Control!$B$2,Control!$B$3,"Dir=V","Dts=H","Sort=A","Per="&Control!$B$6,"Fill=P") -> #NAME? | BC2: =BDH(Universe!B55,Control!$B$5,Control!$B$2,Control!$B$3,"Dir=V","Dts=H","Sort=A","Per="&Control!$B$6,"Fill=P") -> #NAME? | BD2: =BDH(Universe!B56,Control!$B$5,Control!$B$2,Control!$B$3,"Dir=V","Dts=H","Sort=A","Per="&Control!$B$6,"Fill=P") -> #NAME? | BE2: =BDH(Universe!B57,Control!$B$5,Control!$B$2,Control!$B$3,"Dir=V","Dts=H","Sort=A","Per="&Control!$B$6,"Fill=P") -> #NAME? | BF2: =BDH(Universe!B58,Control!$B$5,Control!$B$2,Control!$B$3,"Dir=V","Dts=H","Sort=A","Per="&Control!$B$6,"Fill=P") -> #NAME? | BG2: =BDH(Universe!B59,Control!$B$5,Control!$B$2,Control!$B$3,"Dir=V","Dts=H","Sort=A","Per="&Control!$B$6,"Fill=P") -> #NAME? | BH2: =BDH(Universe!B60,Control!$B$5,Control!$B$2,Control!$B$3,"Dir=V","Dts=H","Sort=A","Per="&Control!$B$6,"Fill=P") -> #NAME? | BI2: =BDH(Universe!B61,Control!$B$5,Control!$B$2,Control!$B$3,"Dir=V","Dts=H","Sort=A","Per="&Control!$B$6,"Fill=P") -> #NAME? | BJ2: =BDH(Universe!B62,Control!$B$5,Control!$B$2,Control!$B$3,"Dir=V","Dts=H","Sort=A","Per="&Control!$B$6,"Fill=P") -> #NAME? | BK2: =BDH(Universe!B63,Control!$B$5,Control!$B$2,Control!$B$3,"Dir=V","Dts=H","Sort=A","Per="&Control!$B$6,"Fill=P") -> #NAME? | BL2: =BDH(Universe!B64,Control!$B$5,Control!$B$2,Control!$B$3,"Dir=V","Dts=H","Sort=A","Per="&Control!$B$6,"Fill=P") -> #NAME? | BM2: =BDH(Universe!B65,Control!$B$5,Control!$B$2,Control!$B$3,"Dir=V","Dts=H","Sort=A","Per="&Control!$B$6,"Fill=P") -> #NAME? | BN2: =BDH(Universe!B66,Control!$B$5,Control!$B$2,Control!$B$3,"Dir=V","Dts=H","Sort=A","Per="&Control!$B$6,"Fill=P") -> #NAME? | BO2: =BDH(Universe!B67,Control!$B$5,Control!$B$2,Control!$B$3,"Dir=V","Dts=H","Sort=A","Per="&Control!$B$6,"Fill=P") -> #NAME? | BP2: =BDH(Universe!B68,Control!$B$5,Control!$B$2,Control!$B$3,"Dir=V","Dts=H","Sort=A","Per="&Control!$B$6,"Fill=P") -> #NAME? | BQ2: =BDH(Universe!B69,Control!$B$5,Control!$B$2,Control!$B$3,"Dir=V","Dts=H","Sort=A","Per="&Control!$B$6,"Fill=P") -> #NAME? | BR2: =BDH(Universe!B70,Control!$B$5,Control!$B$2,Control!$B$3,"Dir=V","Dts=H","Sort=A","Per="&Control!$B$6,"Fill=P") -> #NAME? | BS2: =BDH(Universe!B71,Control!$B$5,Control!$B$2,Control!$B$3,"Dir=V","Dts=H","Sort=A","Per="&Control!$B$6,"Fill=P") -> #NAME? | BT2: =BDH(Universe!B72,Control!$B$5,Control!$B$2,Control!$B$3,"Dir=V","Dts=H","Sort=A","Per="&Control!$B$6,"Fill=P") -> #NAME? | BU2: =BDH(Universe!B73,Control!$B$5,Control!$B$2,Control!$B$3,"Dir=V","Dts=H","Sort=A","Per="&Control!$B$6,"Fill=P") -> #NAME? | BV2: =BDH(Universe!B74,Control!$B$5,Control!$B$2,Control!$B$3,"Dir=V","Dts=H","Sort=A","Per="&Control!$B$6,"Fill=P") -> #NAME? | BW2: =BDH(Universe!B75,Control!$B$5,Control!$B$2,Control!$B$3,"Dir=V","Dts=H","Sort=A","Per="&Control!$B$6,"Fill=P") -> #NAME? | BX2: =BDH(Universe!B76,Control!$B$5,Control!$B$2,Control!$B$3,"Dir=V","Dts=H","Sort=A","Per="&Control!$B$6,"Fill=P") -> #NAME? | BY2: =BDH(Universe!B77,Control!$B$5,Control!$B$2,Control!$B$3,"Dir=V","Dts=H","Sort=A","Per="&Control!$B$6,"Fill=P") -> #NAME? | BZ2: =BDH(Universe!B78,Control!$B$5,Control!$B$2,Control!$B$3,"Dir=V","Dts=H","Sort=A","Per="&Control!$B$6,"Fill=P") -> #NAME? | CA2: =BDH(Universe!B79,Control!$B$5,Control!$B$2,Control!$B$3,"Dir=V","Dts=H","Sort=A","Per="&Control!$B$6,"Fill=P") -> #NAME? | CB2: =BDH(Universe!B80,Control!$B$5,Control!$B$2,Control!$B$3,"Dir=V","Dts=H","Sort=A","Per="&Control!$B$6,"Fill=P") -> #NAME?

Sheet Book_Notes
A1: Book sheet notes
A2: Field: BOOK_VAL_PER_SH (Control!B5), Period: BQ (Control!B6).
A3: Same spill layout as Prices: A2 = Date|first ticker; C+ = values only.
A4: If BOOK_VAL_PER_SH is blank for REITs, try BOOK_VAL_PER_SH / FUND_NET_ASSET_VAL as fallback on Universe.
A5: Quarterly dates (period ends) are fine — the pipeline forward-fills onto daily prices.

Sheet Categories
A1: Ticker | B1: sector | C1: market_cap
A2: D05.SI | B2: =BDP(Universe!B2,"GICS_SECTOR_NAME") -> #NAME? | C2: =BDP(Universe!B2,"CUR_MKT_CAP") -> #NAME?
A3: O39.SI | B3: =BDP(Universe!B3,"GICS_SECTOR_NAME") -> #NAME? | C3: =BDP(Universe!B3,"CUR_MKT_CAP") -> #NAME?
A4: Z74.SI | B4: =BDP(Universe!B4,"GICS_SECTOR_NAME") -> #NAME? | C4: =BDP(Universe!B4,"CUR_MKT_CAP") -> #NAME?
A5: U11.SI | B5: =BDP(Universe!B5,"GICS_SECTOR_NAME") -> #NAME? | C5: =BDP(Universe!B5,"CUR_MKT_CAP") -> #NAME?
A6: S63.SI | B6: =BDP(Universe!B6,"GICS_SECTOR_NAME") -> #NAME? | C6: =BDP(Universe!B6,"CUR_MKT_CAP") -> #NAME?
A7: S68.SI | B7: =BDP(Universe!B7,"GICS_SECTOR_NAME") -> #NAME? | C7: =BDP(Universe!B7,"CUR_MKT_CAP") -> #NAME?
A8: J36.SI | B8: =BDP(Universe!B8,"GICS_SECTOR_NAME") -> #NAME? | C8: =BDP(Universe!B8,"CUR_MKT_CAP") -> #NAME?
A9: C6L.SI | B9: =BDP(Universe!B9,"GICS_SECTOR_NAME") -> #NAME? | C9: =BDP(Universe!B9,"CUR_MKT_CAP") -> #NAME?
A10: F34.SI | B10: =BDP(Universe!B10,"GICS_SECTOR_NAME") -> #NAME? | C10: =BDP(Universe!B10,"CUR_MKT_CAP") -> #NAME?
A11: H78.SI | B11: =BDP(Universe!B11,"GICS_SECTOR_NAME") -> #NAME? | C11: =BDP(Universe!B11,"CUR_MKT_CAP") -> #NAME?
A12: BN4.SI | B12: =BDP(Universe!B12,"GICS_SECTOR_NAME") -> #NAME? | C12: =BDP(Universe!B12,"CUR_MKT_CAP") -> #NAME?
A13: C38U.SI | B13: =BDP(Universe!B13,"GICS_SECTOR_NAME") -> #NAME? | C13: =BDP(Universe!B13,"CUR_MKT_CAP") -> #NAME?
... A80: DCRU.SI | B80: =BDP(Universe!B80,"GICS_SECTOR_NAME") -> #NAME? | C80: =BDP(Universe!B80,"CUR_MKT_CAP") -> #NAME?

Sheet Categories_Notes
A1: Categories notes
A2: Export this sheet as categorizations_data.csv (headers: Ticker,sector,market_cap).
A3: If GICS_SECTOR_NAME is empty, switch formula to INDUSTRY_SECTOR or CLASSIFICATION_LEVEL_1_NAME.
A4: market_cap should be absolute CUR_MKT_CAP (same units across names).

Sheet Dividends
A1: Dividend pull helper (one ticker at a time)
A3: SelectYahoo | B3: D05.SI
A4: BloombergTicker | B4: =IFERROR(INDEX(Universe!B:B,MATCH(B3,Universe!A:A,0)),"") -> D05 SP Equity
A5: History formula (paste below)
A6: =BDS(B4,"DVD_HIST_ALL","Headers=Y") -> #NAME?
A8: Instructions
A9: 1. Change B3 to a Yahoo ticker (e.g. D05.SI).
A10: 2. Refresh — BDS spills Ex Date / Dividend Amount / Dividend Type / etc.
A11: 3. Copy Ex-Date + Dividend Amount for each ticker into a long table:
A12: Date,Ticker,DPS
A13: 4. Run bbg_to_csv.py — it pivots long dividends into wide dividend_data.csv.
A15: Optional bulk: use Bloomberg Excel Template Library → Dividend History, then map columns.
A17: Long_Table_Headers → | B17: Date | C17: Ticker | D17: DPS
A18: Paste rows starting at B18 (Date | YahooTicker | Dividend Amount)

Sheet Dividend_Tickers
A1: YahooTicker | B1: BloombergTicker | C1: Pulled?
A2: D05.SI | B2: D05 SP Equity
A3: O39.SI | B3: O39 SP Equity
A4: Z74.SI | B4: Z74 SP Equity
A5: U11.SI | B5: U11 SP Equity
A6: S63.SI | B6: S63 SP Equity
A7: S68.SI | B7: S68 SP Equity
A8: J36.SI | B8: J36 SP Equity
A9: C6L.SI | B9: C6L SP Equity
A10: F34.SI | B10: F34 SP Equity
A11: H78.SI | B11: H78 SP Equity
A12: BN4.SI | B12: BN4 SP Equity
A13: C38U.SI | B13: C38U SP Equity
... A80: DCRU.SI | B80: DCRU SP Equity

Sheet Export_Checklist
A1: Export checklist → data/sg/raw/
A3: After all sheets show numbers (not #N/A Requesting Data...):
A5: Option A — Automated (recommended)
A6: 1. Save this workbook (formulas calculated / values cached).
A7: 2. In Excel: File → Save As → Excel Workbook (keep .xlsx).
A8: 3. Optional: copy Prices/Book/Categories and Paste Values to freeze.
A9: 4. Run:
A10: python bloomberg/bbg_to_csv.py --xlsx bloomberg/SG_Bloomberg_Historical_Pull.xlsx
A11: 5. Confirm files appear in data/sg/raw/:
A12: price_data.csv, book_data.csv, categorizations_data.csv [, dividend_data.csv]
A13: 6. Run pipeline:
A14: python main.py --market sg --skip-download
... A25: • categorizations_data.csv columns = Ticker,sector,market_cap
